controller2/target.v
module Target_Controller(
    input clk, inout[31:0] AD, input[3:0] C_BE, output devsel, output trdy, input[2:0] state, input fvalid
    );

parameter[3:0]
/* Command value for read = 1, write = 0 */
read = 1, write = 0;

parameter[2:0] idle=0, address=1, turnaround=2, data=3, finish=4;
parameter[31:0] devaddress = 1;
reg[31:0] add;
reg[31:0] memory;
reg[3:0] command;
always @ (posedge clk) begin
    if (state == address) begin
        add <= AD;
        command <= C_BE; 
    end
    if(state == data && command == write) begin
        if(C_BE[0]) begin
            memory[7:0] <= AD[7:0]; 
        end
        if(C_BE[1]) begin
            memory[15:8] <= AD[15:8];  
        end
        if(C_BE[2]) begin
            memory[23:16] <= AD[23:16];  
        end
        if(C_BE[3]) begin
            memory[31:24] <= AD[31:24];  
        end
    end
end

assign devsel = (state == data && add == devaddress) ? 0 : (state == finish || state == turnaround) ? 1 : 1'bz;
assign trdy = (state == data && add == devaddress) ? 0 : (state == finish || state == turnaround) ? 1 : 1'bz;
assign AD = (state == data && add == devaddress && command == read) ?  32'hAAAAAAAA: 32'hZZZZZZZZ;

endmodule   //target read module

controller2/initiator.v
module Initiator_Controller(
    input [1:0]devaddress, input [3:0] BE, input force_req, input rd_wr, input[31:0] write_data,
    input clk, inout[31:0] AD, output[3:0] C_BE, output frame, output irdy,
    output req,
    input[2:0] state, input fcount, input fend_count, input ffinished, input fvalid
    );

reg[3:0] command;
reg[3:0] byte_enable[7:0];
always @ (posedge clk) begin
    if (force_req) begin
        memory[7] <= devaddress;
        command <= rd_wr;
        memory[counter] <= write_data;
        byte_enable[counter] <= BE;
    end
end

parameter[2:0]
idle=0, address=1, turnaround=2, data=3, finish=4;

/*************************** count number of required transactions by master ******************************/
/* frame must not get asserted before force_req signal gets deasserted */
reg [1:0] counter;
always @ (negedge clk) begin
    if(fcount) begin     
        counter = counter + 1; 
    end
    if (state == data && fvalid && bus_is_mine) begin
        counter = counter - 1; 
    end
end
always @ (posedge force_req) begin
    counter <= 0;
end

////////////////////////////////////* send request to arbiter *////////////////////////////////////////////////
reg bus_is_mine;    // indicate whether the bus is in this controller's command (active high)
assign req = (fend_count && (counter > 1 || ((!bus_is_mine || state == finish) && counter))) ? 0 : 1; // MUST REVIEW
always @ (*) begin
    if (fcount) begin
        bus_is_mine = 0; 
    end
    if (state == address) begin
        bus_is_mine = 1; 
    end
    if (bus_is_mine && ffinished) begin
        bus_is_mine = 0; 
    end
end

////////////////////////////////////////////* set frame *////////////////////////////////////////////////////
assign frame = (bus_is_mine && state != finish) ? ( (state == address || counter > 1) ? 0 : 1) : 1'bz;  //multi transactions 

///////////////////////////////////////////* set AD with address *//////////////////////////////////////////
assign AD = (state == address && bus_is_mine) ? memory[7] : (command == 0 && state == data) ? memory[mp] : 32'hZZZZZZZZ;
assign C_BE = (state == address && bus_is_mine) ? command : (state == data) ? byte_enable[mp] : 4'bzzzz;

////////////////////////////////////////////* set irdy *////////////////////////////////////////////////////
assign irdy = (bus_is_mine && (state == turnaround || state == data)) ? 0 : ( (bus_is_mine && state == finish) ? 1 : 1'bz );

////////////////////////////////////////////* read data *////////////////////////////////////////////////////
reg[2:0] mp;            //memory pointer
reg[31:0] memory[9:0];  //multi transaction 
wire[31:0] mem1, mem2, mem3, mem4;
assign mem1 = memory[0];
assign mem2 = memory[1];
assign mem3 = memory[2];
assign mem4 = memory[3];

always @ (posedge clk) begin
    if (bus_is_mine && (state == data && fvalid) && command == 1) begin
        memory[mp] <= AD;
    end
    if (state == idle && counter == 0) begin
        mp <= 0; 
    end
end
always @ (negedge clk) begin    // increment memory pointer
    if (bus_is_mine && (state == data && fvalid)) begin
        mp <= mp + 1; 
    end
end

endmodule   //master read module

controller2/state_machine2.v
module State_Machine(
    frame, irdy, trdy, devsel, state, clk, force_req, req, gnt, rd_wr, fcount, fend_count, ffinished, fvalid
);

/*
    This state machine is valid for both read and write transactions
    for read: rd_wr = 1
    for write: rd_wr = 0
*/

input wire frame, irdy, trdy, devsel, clk, force_req, req, gnt, rd_wr;
output reg[2:0] state;
reg[2:0] next_state;

parameter[2:0] 
/*
There are five states:
1. idle: here the bus is free (with respect to the device)
2. address: the initiator has asserted the frame and put a valid address on AD lines
3. turnaround: in case of read transaction the target must wait for two cylces after the frame being asserted
    to put valid data on AD and hence assert trdy
4. data: here data tranfers may occur depending on irdy & trdy (fvalid flag)
5. finish: all required transfers have occured and turnaround cycle ouccurs 
*/
idle=0, address=1, turnaround=2, data=3, finish=4;

output reg          //flags that contributes in synchronization of bus lines
    fcount,         //indicates assertion of force_req signal
    fend_count,     //indicates deassertion of force_req signal
    ffinished,      //indicates finished transaction and free bus
    fvalid;         //indicates that a valid data transfer may occur next positive edge of clock **combinational
reg fgnt;           //indicates a granted bus ownership

always @(negedge clk) begin
    state <= next_state;
    if (force_req) begin
        fend_count <= 0;
        fcount <= 1; 
    end
    if (!force_req && fcount) begin
        fcount <= 0;
        fend_count <= 1;
    end
    if (state == address) begin
        ffinished <= 0; 
    end
    if (state == finish) begin
        ffinished <= 1;
    end
    if (!gnt) begin
        fgnt <= 1; 
    end else begin
        fgnt <= 0; 
    end
end

always @(*) begin
    case (state)

        idle: if (fgnt && !req) begin
            next_state = address;
        end

        address: begin
            if (!frame) begin
                if (rd_wr) begin
                    next_state = turnaround;               
                end
                else begin
                    next_state = data;
                end
            end
        end

        turnaround: begin
            next_state = data;
        end

        data: begin
            if(~fgnt) begin
                next_state = finish; 
            end
            if (frame) begin
                next_state = finish; 
            end
            if(!trdy && !irdy) begin
                fvalid = 1; 
            end else begin
                fvalid = 0; 
            end
        end

        finish: begin 
            next_state = idle; 
        end

        default: next_state = idle; //for initializing
    endcase
end

endmodule // State_Machine

controller2/device.v
module Controller(
    input [1:0]devaddress, input [3:0] BE, input force_req, input rd_wr, input[31:0]  write_data,
    input clk, inout[31:0] AD, inout[3:0] C_BE, inout devsel, inout frame, inout irdy, inout trdy,
    input gnt, output req
);

wire[2:0] state;

State_Machine sm(
    frame, irdy, trdy, devsel, state, clk, force_req, req, gnt, rd_wr, fcount, fend_count, ffinished, fvalid
);

Initiator_Controller ic(
    devaddress, BE, force_req, rd_wr, write_data, clk, AD, C_BE, frame, irdy, req, 
    state, fcount, fend_count, ffinished, fvalid
);

Target_Controller tc(
    clk, AD, C_BE, devsel, trdy, state, fvalid
);


endmodule

controller2/initiator_tb.v
`timescale 1us/1us
module test;
    reg[1:0] address;
    reg[31:0] dat;
    reg[3:0] BE;
    wire[3:0] C_BE;
    reg force_req, clk, gnt, rd_wr;
    wire frame, irdy, req;
    wire[31:0] d;
    initial begin
        $dumpfile("test.vcd");
        $dumpvars(0,test);
        gnt = 1; force_req = 0; rd_wr = 1;
        clk = 0;
        #4
        force_req = 1;
        address = 2'b01;
        dat = 32'hBBBBDFBB;
        BE = 4'b1011;
        #2
        dat = 32'hAAAAAAAA;
        BE = 4'b0001;
        #2
        dat = 32'hBBBBDFBB;
        BE = 4'b0100;
        #2
        force_req = 0;
        address = 2'bzz;
        dat = 32'hZZZZZZZZ;
        BE = 4'bzzzz;
        #2
        gnt = 0;
        // #6
        // gnt = 1;
        // #2
        // gnt = 0;
        // #4
        // gnt = 1;
        // #4
        // gnt = 0;
        
        # 30 $finish;
    end

    always #1 clk = ~clk;

    Controller device( address,  BE,  force_req,  rd_wr, dat,
     clk,  d,  C_BE,  devsel,  frame,  irdy,  trdy,
     gnt,  req);

endmodule //

controller2/test.vcd
$date
	Sun Dec 23 22:56:27 2018
$end
$version
	Icarus Verilog
$end
$timescale
	1us
$end
$scope module test $end
$var wire 32 ! d [31:0] $end
$var wire 1 " trdy $end
$var wire 1 # req $end
$var wire 1 $ irdy $end
$var wire 1 % frame $end
$var wire 1 & devsel $end
$var wire 4 ' C_BE [3:0] $end
$var reg 4 ( BE [3:0] $end
$var reg 2 ) address [1:0] $end
$var reg 1 * clk $end
$var reg 32 + dat [31:0] $end
$var reg 1 , force_req $end
$var reg 1 - gnt $end
$var reg 1 . rd_wr $end
$scope module device $end
$var wire 32 / AD [31:0] $end
$var wire 4 0 BE [3:0] $end
$var wire 1 * clk $end
$var wire 2 1 devaddress [1:0] $end
$var wire 1 , force_req $end
$var wire 1 - gnt $end
$var wire 1 . rd_wr $end
$var wire 32 2 write_data [31:0] $end
$var wire 1 " trdy $end
$var wire 3 3 state [2:0] $end
$var wire 1 # req $end
$var wire 1 $ irdy $end
$var wire 1 4 fvalid $end
$var wire 1 % frame $end
$var wire 1 5 ffinished $end
$var wire 1 6 fend_count $end
$var wire 1 7 fcount $end
$var wire 1 & devsel $end
$var wire 4 8 C_BE [3:0] $end
$scope module ic $end
$var wire 32 9 AD [31:0] $end
$var wire 4 : BE [3:0] $end
$var wire 1 * clk $end
$var wire 2 ; devaddress [1:0] $end
$var wire 1 , force_req $end
$var wire 32 < mem1 [31:0] $end
$var wire 32 = mem2 [31:0] $end
$var wire 32 > mem3 [31:0] $end
$var wire 32 ? mem4 [31:0] $end
$var wire 1 . rd_wr $end
$var wire 32 @ write_data [31:0] $end
$var wire 3 A state [2:0] $end
$var wire 1 # req $end
$var wire 1 $ irdy $end
$var wire 1 4 fvalid $end
$var wire 1 % frame $end
$var wire 1 5 ffinished $end
$var wire 1 6 fend_count $end
$var wire 1 7 fcount $end
$var wire 4 B C_BE [3:0] $end
$var reg 1 C bus_is_mine $end
$var reg 4 D command [3:0] $end
$var reg 2 E counter [1:0] $end
$var reg 3 F mp [2:0] $end
$upscope $end
$scope module sm $end
$var wire 1 * clk $end
$var wire 1 , force_req $end
$var wire 1 % frame $end
$var wire 1 - gnt $end
$var wire 1 $ irdy $end
$var wire 1 . rd_wr $end
$var wire 1 # req $end
$var wire 1 " trdy $end
$var wire 1 & devsel $end
$var reg 1 7 fcount $end
$var reg 1 6 fend_count $end
$var reg 1 5 ffinished $end
$var reg 1 G fgnt $end
$var reg 1 4 fvalid $end
$var reg 3 H next_state [2:0] $end
$var reg 3 I state [2:0] $end
$upscope $end
$scope module tc $end
$var wire 32 J AD [31:0] $end
$var wire 4 K C_BE [3:0] $end
$var wire 1 * clk $end
$var wire 1 4 fvalid $end
$var wire 3 L state [2:0] $end
$var wire 1 " trdy $end
$var wire 1 & devsel $end
$var reg 32 M add [31:0] $end
$var reg 4 N command [3:0] $end
$var reg 32 O memory [31:0] $end
$upscope $end
$upscope $end
$upscope $end
$enddefinitions $end
#0
$dumpvars
bx O
bx N
bx M
b0 L
bz K
bz J
b0 I
b0 H
0G
bx F
bx E
bx D
xC
bz B
b0 A
bx @
bx ?
bx >
bx =
bx <
bx ;
bx :
bz 9
bz 8
x7
x6
x5
x4
b0 3
bx 2
bx 1
bx 0
bz /
1.
1-
0,
bx +
0*
bx )
bx (
bz '
z&
x%
z$
x#
z"
bz !
$end
#1
1*
#2
0*
#3
1*
#4
z%
1#
0C
17
06
b0 E
0*
b1011 (
b1011 0
b1011 :
b10111011101110111101111110111011 +
b10111011101110111101111110111011 2
b10111011101110111101111110111011 @
b1 )
b1 1
b1 ;
1,
#5
b10111011101110111101111110111011 <
b1 D
b0 F
1*
#6
b1 E
0*
b1 (
b1 0
b1 :
b10101010101010101010101010101010 +
b10101010101010101010101010101010 2
b10101010101010101010101010101010 @
#7
b10101010101010101010101010101010 =
1*
#8
b10 E
0*
b100 (
b100 0
b100 :
b10111011101110111101111110111011 +
b10111011101110111101111110111011 2
b10111011101110111101111110111011 @
#9
b10111011101110111101111110111011 >
1*
#10
0#
16
07
b11 E
0*
bz (
bz 0
bz :
bz +
bz 2
bz @
bz )
bz 1
bz ;
0,
#11
1*
#12
b1 H
1G
0*
0-
#13
1*
#14
b10 H
0%
b1 '
b1 8
b1 B
b1 K
b1 !
b1 /
b1 9
b1 J
1C
b1 3
b1 A
b1 I
b1 L
0*
#15
b1 N
b1 M
1*
#16
1&
1"
0$
bz '
bz 8
bz B
bz K
bz !
bz /
bz 9
bz J
b11 H
05
b10 3
b10 A
b10 I
b10 L
0*
#17
1*
#18
0&
0"
b10101010101010101010101010101010 !
b10101010101010101010101010101010 /
b10101010101010101010101010101010 9
b10101010101010101010101010101010 J
b1011 '
b1011 8
b1011 B
b1011 K
14
b11 3
b11 A
b11 I
b11 L
0*
#19
b10101010101010101010101010101010 <
1*
#20
b1 '
b1 8
b1 B
b1 K
b1 F
b10 E
0*
#21
1*
#22
b100 '
b100 8
b100 B
b100 K
b10 F
b100 H
1#
1%
b1 E
0*
#23
b10101010101010101010101010101010 >
1*
#24
1$
1&
1"
bz !
bz /
bz 9
bz J
z%
bz '
bz 8
bz B
bz K
b0 H
b100 3
b100 A
b100 I
b100 L
b11 F
b0 E
0*
#25
1*
#26
z&
z"
z$
0C
15
b0 3
b0 A
b0 I
b0 L
0*
#27
b0 F
1*
