device/target.v
module Target_Controller(
    input clk, inout[31:0] AD, input[3:0] C_BE, output devsel, output trdy, input[2:0] state, input fvalid, input[1:0] tar_address
    );

parameter[3:0]
/* Command value for read = 1, write = 0 */
read = 1, write = 0;

parameter[2:0] idle=0, address=1, turnaround=2, data=3, finish=4;
reg[31:0] add;
reg[31:0] memory;
reg[3:0] command;
always @ (posedge clk) begin
    if (state == address) begin
        add <= AD;
        command <= C_BE; 
    end
    if(state == data && command == write) begin
        if(C_BE[0]) begin
            memory[7:0] <= AD[7:0]; 
        end
        if(C_BE[1]) begin
            memory[15:8] <= AD[15:8];  
        end
        if(C_BE[2]) begin
            memory[23:16] <= AD[23:16];  
        end
        if(C_BE[3]) begin
            memory[31:24] <= AD[31:24];  
        end
    end
end

assign devsel = (state == data && add === tar_address) ? 0 : ((state == finish || state == turnaround) && add === tar_address) ? 1 : 1'bz;
assign trdy = (state == data && add === tar_address) ? 0 : ((state == finish || state == turnaround) && add === tar_address) ? 1 : 1'bz;
assign AD = (state == data && add === tar_address && command == read) ?  32'hAAAAAAAA: 32'hZZZZZZZZ;

endmodule   //target read module

device/initiator.v
module Initiator_Controller(
    input [1:0]devaddress, input [3:0] BE, input force_req, input rd_wr, input[31:0] write_data,
    input clk, inout[31:0] AD, output[3:0] C_BE, output frame, output irdy,
    output req,
    input[2:0] state, input fcount, input fend_count, input ffinished, input fvalid,
    input fburst    // extra input for burst read (active high)
    );

/*
  **When in burst mode the intiator continues in data phases until either maximum failed transfers 
    or fburst signalis deasserted.
  **In Normal mode the intiator completes one data transfer and continues to the next transaction.
*/

reg[3:0] command;
reg[3:0] byte_enable[7:0];
/*
    when force_req signal is asserted, at every positive edge a corresponding target-address and command is saved
    in internal memory  
*/
always @ (posedge clk) begin
    if (force_req) begin
        memory[9 - counter] <= devaddress;
        command <= rd_wr;
    end
end

parameter[2:0]    
idle=0, address=1, turnaround=2, data=3, finish=4;  //states are declared in State_Machine module

/*************************** count number of required transactions by master ******************************/
            /* frame shall not get asserted before force_req signal gets deasserted */

reg[2:0] failed_counter;        //count the cycles at which the target hasn't responded ** max limit 5 cycles
reg [1:0] counter, max;         //counts and saves the number of required transactions
always @ (negedge clk) begin
    if(fcount) begin     
        counter <= counter + 1; 
        max <= counter + 1;
        failed_counter <= 0;
    end
    if (state == finish && !fburst && bus_is_mine) begin
        counter <= counter - 1; 
        failed_counter <= 0;
    end
    if (state == data && !fvalid) begin
        failed_counter <= failed_counter + 1;
    end
    if (state == data && fvalid) begin
        failed_counter <= 0;
    end
end
always @ (posedge force_req) begin
    counter <= 0;
    max <= 0;  
end

////////////////////////////////////* send request to arbiter *////////////////////////////////////////////////
reg bus_is_mine;    // indicate whether the bus is in this controller's command (active high)
assign req = (fend_count === 1 && ((counter && (fburst || failed_counter < 4 || !bus_is_mine)) || counter > 1)) ? 0 : 1; // MUST REVIEW
always @ (*) begin
    if (fcount) begin
        bus_is_mine = 0; 
    end
    if (state == address) begin
        bus_is_mine = 1; 
    end
    if (bus_is_mine && ffinished) begin
        bus_is_mine = 0; 
    end
end

////////////////////////////////////////////* set frame *////////////////////////////////////////////////////
assign frame = (bus_is_mine === 1 && state != finish && counter) ? ( (state == address || fburst || failed_counter < 4) ? 0 : 1) : 1'bz;  //multi transactions 

///////////////////////////////////////////* set AD with address *//////////////////////////////////////////
assign AD = (state == address && bus_is_mine === 1) ? memory[9 - max + counter] : (command === 0 && state === data) ? write_data : 32'hZZZZZZZZ;
assign C_BE = (state == address && bus_is_mine === 1) ? command : (state === data) ? BE : 4'bzzzz;

////////////////////////////////////////////* set irdy *////////////////////////////////////////////////////
assign irdy = (bus_is_mine === 1 && (state == turnaround || state == data)) ? 0 : ( (bus_is_mine === 1 && state == finish) ? 1 : 1'bz );

////////////////////////////////////////////* read data *////////////////////////////////////////////////////
                            /* read data is saved in this internal memory */

reg[2:0] mp;            //memory pointer
reg[31:0] memory[9:0];  //multi transaction 
wire[31:0] mem1, mem2, mem3, mem4, mem9, mem10;
assign mem1 = memory[0];
assign mem2 = memory[1];
assign mem3 = memory[2];
assign mem4 = memory[3];
assign mem9 = memory[8];
assign mem10 = memory[9];

always @ (posedge clk) begin
    if (bus_is_mine && (state == data && fvalid) && command == 1) begin
        memory[mp] <= AD;
    end
    if (state == idle && counter == 0) begin
        mp <= 0; 
    end
end
always @ (negedge clk) begin    // increment memory pointer
    if (bus_is_mine && (state == data && fvalid) && mp < 8) begin
        mp <= mp + 1; 
    end
end

endmodule   //master read & write module

controller2/state_machine2.v
module State_Machine(
    frame, irdy, trdy, devsel, state, clk, force_req, burst, req, gnt, rd_wr, fcount, fend_count, ffinished, fvalid, fburst
);

/*
    This state machine is valid for both read and write transactions
    for read: rd_wr = 1
    for write: rd_wr = 0
*/

input wire frame, irdy, trdy, devsel, clk, force_req, burst, req, gnt, rd_wr;
output reg[2:0] state;
reg[2:0] next_state;

parameter[2:0] 
/*
There are five states:
1. idle: here the bus is free (with respect to the device)
2. address: the initiator has asserted the frame and put a valid address on AD lines
3. turnaround: in case of read transaction the target must wait for two cylces after the frame being asserted
    to put valid data on AD and hence assert trdy
4. data: here data tranfers may occur depending on irdy & trdy (fvalid flag)
5. finish: all required transfers have occured and turnaround cycle ouccurs 
*/
idle=0, address=1, turnaround=2, data=3, finish=4;

output reg          //flags that contributes in synchronization of bus lines
    fcount,         //indicates assertion of force_req signal
    fend_count,     //indicates deassertion of force_req signal
    ffinished,      //indicates finished transaction and free bus
    fvalid,         //indicates that a valid data transfer may occur next positive edge of clock **combinational
    fburst;
reg fgnt;           //indicates a granted bus ownership

always @(negedge clk) begin
    state <= next_state;
    if (force_req) begin
        fend_count <= 0;
        fcount <= 1; 
    end
    if (!force_req && fcount) begin
        fcount <= 0;
        fend_count <= 1;
    end
    if (state == address) begin
        ffinished <= 0; 
    end
    if (state == finish) begin
        ffinished <= 1;
    end
    if (!gnt) begin
        fgnt <= 1; 
    end else begin
        fgnt <= 0; 
    end
    if (burst) begin
        fburst <= 1; 
    end else begin
        fburst <= 0; 
    end
end

always @(*) begin
    case (state)

        idle: if (fgnt && !req) begin
            next_state = address;
        end

        address: begin
            if (!frame) begin
                if (rd_wr) begin
                    next_state = turnaround;               
                end
                else begin
                    next_state = data;
                end
            end
        end

        turnaround: begin
            next_state = data;
        end

        data: begin
            if(~fgnt) begin
                next_state = finish; 
            end
            if (frame) begin
                next_state = finish; 
            end
            if(!trdy && !irdy) begin
                fvalid = 1; 
            end else begin
                fvalid = 0; 
            end
        end

        finish: begin 
            next_state = idle; 
        end

        default: next_state = idle; //for initializing
    endcase
end

endmodule // State_Machine

device/device.v
module Controller(
    input [1:0]devaddress, input [3:0] BE, input force_req, input rd_wr, input[31:0]  write_data, input burst,
    input clk, inout[31:0] AD, inout[3:0] C_BE, inout devsel, inout frame, inout irdy, inout trdy,
    input gnt, output req,
    input reset_address //active high
);

wire[2:0] state;
reg[1:0] tar_add;
always @ (reset_address) begin
    if (reset_address) begin
        tar_add <= devaddress;
    end
end

State_Machine sm(
    frame, irdy, trdy, devsel, state, clk, force_req, burst, req, gnt, rd_wr, fcount, fend_count, ffinished, fvalid, fburst
);

Initiator_Controller ic(
    devaddress, BE, force_req, rd_wr, write_data, clk, AD, C_BE, frame, irdy, req, 
    state, fcount, fend_count, ffinished, fvalid, fburst
);

Target_Controller tc(
    clk, AD, C_BE, devsel, trdy, state, fvalid, tar_add
);


endmodule

controller2/initiator_tb.v
`timescale 1us/1us
module test;
    reg[1:0] address;
    reg[31:0] dat;
    reg[3:0] BE;
    wire[3:0] C_BE;
    reg force_req, clk, gnt, rd_wr, burst, rframe, reset_add;
    inout frame, irdy, req;
    assign frame = rframe;
    wire[31:0] d;
    initial begin
        $dumpfile("test.vcd");
        $dumpvars(0,test);
        rframe = 1'bz;
        gnt = 1; force_req = 0; rd_wr = 0; burst = 1; reset_add = 1; address = 2'b01;
        clk = 0;
        #4
        reset_add = 0;
        force_req = 1;
        address = 2'b10;
        dat = 32'hBBBBDFBB;
        BE = 4'b1011;
        #2
        dat = 32'hAAAAAAAA;
        BE = 4'b0001;
        #2
        dat = 32'hBBBBDFBB;
        BE = 4'b0100;
        #2
        force_req = 0;
        address = 2'bzz;
        // dat = 32'hZZZZZZZZ;
        // BE = 4'bzzzz;

        #6
        gnt = 1;
        #2
        gnt = 0;
        #4
        gnt = 1;
        #4
        gnt = 0;
        burst = 0;
        
        # 80 $finish;
    end

    always #1 clk = ~clk;

    Controller device( address,  BE,  force_req,  rd_wr, dat, burst,
     clk,  d,  C_BE,  devsel,  frame,  irdy,  trdy,
     gnt,  req,
     reset_add
     );

endmodule //

controller2/test.vcd
$date
	Mon Dec 24 21:35:11 2018
$end
$version
	Icarus Verilog
$end
$timescale
	1us
$end
$scope module test $end
$var wire 32 ! d [31:0] $end
$var wire 1 " frame $end
$var wire 1 # trdy $end
$var wire 1 $ req $end
$var wire 1 % irdy $end
$var wire 1 & devsel $end
$var wire 4 ' C_BE [3:0] $end
$var reg 4 ( BE [3:0] $end
$var reg 2 ) address [1:0] $end
$var reg 1 * burst $end
$var reg 1 + clk $end
$var reg 32 , dat [31:0] $end
$var reg 1 - force_req $end
$var reg 1 . gnt $end
$var reg 1 / rd_wr $end
$var reg 1 0 reset_add $end
$var reg 1 1 rframe $end
$scope module device $end
$var wire 32 2 AD [31:0] $end
$var wire 4 3 BE [3:0] $end
$var wire 1 * burst $end
$var wire 1 + clk $end
$var wire 2 4 devaddress [1:0] $end
$var wire 1 - force_req $end
$var wire 1 " frame $end
$var wire 1 . gnt $end
$var wire 1 / rd_wr $end
$var wire 1 0 reset_address $end
$var wire 32 5 write_data [31:0] $end
$var wire 1 # trdy $end
$var wire 3 6 state [2:0] $end
$var wire 1 $ req $end
$var wire 1 % irdy $end
$var wire 1 7 fvalid $end
$var wire 1 8 ffinished $end
$var wire 1 9 fend_count $end
$var wire 1 : fcount $end
$var wire 1 ; fburst $end
$var wire 1 & devsel $end
$var wire 4 < C_BE [3:0] $end
$var reg 2 = tar_add [1:0] $end
$scope module ic $end
$var wire 32 > AD [31:0] $end
$var wire 4 ? BE [3:0] $end
$var wire 1 + clk $end
$var wire 2 @ devaddress [1:0] $end
$var wire 1 - force_req $end
$var wire 1 " frame $end
$var wire 32 A mem1 [31:0] $end
$var wire 32 B mem10 [31:0] $end
$var wire 32 C mem2 [31:0] $end
$var wire 32 D mem3 [31:0] $end
$var wire 32 E mem4 [31:0] $end
$var wire 32 F mem9 [31:0] $end
$var wire 1 / rd_wr $end
$var wire 32 G write_data [31:0] $end
$var wire 3 H state [2:0] $end
$var wire 1 $ req $end
$var wire 1 % irdy $end
$var wire 1 7 fvalid $end
$var wire 1 8 ffinished $end
$var wire 1 9 fend_count $end
$var wire 1 : fcount $end
$var wire 1 ; fburst $end
$var wire 4 I C_BE [3:0] $end
$var reg 1 J bus_is_mine $end
$var reg 4 K command [3:0] $end
$var reg 2 L counter [1:0] $end
$var reg 3 M failed_counter [2:0] $end
$var reg 2 N max [1:0] $end
$var reg 3 O mp [2:0] $end
$upscope $end
$scope module sm $end
$var wire 1 * burst $end
$var wire 1 + clk $end
$var wire 1 - force_req $end
$var wire 1 " frame $end
$var wire 1 . gnt $end
$var wire 1 % irdy $end
$var wire 1 / rd_wr $end
$var wire 1 $ req $end
$var wire 1 # trdy $end
$var wire 1 & devsel $end
$var reg 1 ; fburst $end
$var reg 1 : fcount $end
$var reg 1 9 fend_count $end
$var reg 1 8 ffinished $end
$var reg 1 P fgnt $end
$var reg 1 7 fvalid $end
$var reg 3 Q next_state [2:0] $end
$var reg 3 R state [2:0] $end
$upscope $end
$scope module tc $end
$var wire 32 S AD [31:0] $end
$var wire 4 T C_BE [3:0] $end
$var wire 1 + clk $end
$var wire 1 7 fvalid $end
$var wire 3 U state [2:0] $end
$var wire 2 V tar_address [1:0] $end
$var wire 1 # trdy $end
$var wire 1 & devsel $end
$var reg 32 W add [31:0] $end
$var reg 4 X command [3:0] $end
$var reg 32 Y memory [31:0] $end
$upscope $end
$upscope $end
$upscope $end
$enddefinitions $end
#0
$dumpvars
bx Y
bx X
bx W
b1 V
b0 U
bz T
bz S
b0 R
b0 Q
0P
bx O
bx N
bx M
bx L
bx K
xJ
bz I
b0 H
bx G
bx F
bx E
bx D
bx C
bx B
bx A
b1 @
bx ?
bz >
b1 =
bz <
1;
x:
x9
x8
x7
b0 6
bx 5
b1 4
bx 3
bz 2
z1
10
0/
1.
0-
bx ,
0+
1*
b1 )
bx (
bz '
z&
z%
x$
z#
x"
bz !
$end
#1
1+
#2
0+
#3
1+
#4
1$
z"
0J
1:
09
b0 N
b0 L
0+
b1011 (
b1011 3
b1011 ?
b10111011101110111101111110111011 ,
b10111011101110111101111110111011 5
b10111011101110111101111110111011 G
b10 )
b10 4
b10 @
1-
00
#5
b0 K
b10 B
b0 O
1+
#6
b0 M
b1 N
b1 L
0+
b1 (
b1 3
b1 ?
b10101010101010101010101010101010 ,
b10101010101010101010101010101010 5
b10101010101010101010101010101010 G
#7
b10 F
1+
#8
b10 N
b10 L
0+
b100 (
b100 3
b100 ?
b10111011101110111101111110111011 ,
b10111011101110111101111110111011 5
b10111011101110111101111110111011 G
#9
1+
#10
0$
b11 N
b11 L
19
0:
0+
bz )
bz 4
bz @
0-
#11
1+
#12
0+
#13
1+
#14
0+
#15
1+
#16
0+
#17
1+
#18
b1 Q
1P
0+
0.
#19
1+
#20
b11 Q
0"
b0 '
b0 <
b0 I
b0 T
b10 !
b10 2
b10 >
b10 S
1J
b1 6
b1 H
b1 R
b1 U
0+
#21
b0 X
b10 W
1+
#22
0%
b100 '
b100 <
b100 I
b100 T
b10111011101110111101111110111011 !
b10111011101110111101111110111011 2
b10111011101110111101111110111011 >
b10111011101110111101111110111011 S
07
b100 Q
0P
08
b11 6
b11 H
b11 R
b11 U
0+
1.
#23
bx10111011xxxxxxxxxxxxxxxx Y
1+
#24
1%
z"
bz !
bz 2
bz >
bz S
bz '
bz <
bz I
bz T
b0 Q
b100 6
b100 H
b100 R
b100 U
b1 M
0+
#25
1+
#26
z%
0J
b1 Q
0;
1P
18
b0 6
b0 H
b0 R
b0 U
0+
0*
0.
#27
1+
#28
0J
b1 6
b1 H
b1 R
b1 U
0+
#29
bz X
bz W
1+
#30
b11 Q
0"
b0 '
b0 <
b0 I
b0 T
b10 !
b10 2
b10 >
b10 S
1J
08
0+
#31
b0 X
b10 W
1+
#32
0%
b100 '
b100 <
b100 I
b100 T
b10111011101110111101111110111011 !
b10111011101110111101111110111011 2
b10111011101110111101111110111011 >
b10111011101110111101111110111011 S
b11 6
b11 H
b11 R
b11 U
0+
#33
1+
#34
b10 M
0+
#35
1+
#36
b11 M
0+
#37
1+
#38
b100 Q
1"
b100 M
0+
#39
1+
#40
1%
z"
bz !
bz 2
bz >
bz S
bz '
bz <
bz I
bz T
b0 Q
b100 6
b100 H
b100 R
b100 U
b101 M
0+
#41
1+
#42
z%
0J
b1 Q
b0 M
b10 L
18
b0 6
b0 H
b0 R
b0 U
0+
#43
1+
#44
0J
b1 6
b1 H
b1 R
b1 U
0+
#45
bz X
bz W
1+
#46
b11 Q
0"
b0 '
b0 <
b0 I
b0 T
b10 !
b10 2
b10 >
b10 S
1J
08
0+
#47
b0 X
b10 W
1+
#48
0%
b100 '
b100 <
b100 I
b100 T
b10111011101110111101111110111011 !
b10111011101110111101111110111011 2
b10111011101110111101111110111011 >
b10111011101110111101111110111011 S
b11 6
b11 H
b11 R
b11 U
0+
#49
1+
#50
b1 M
0+
#51
1+
#52
b10 M
0+
#53
1+
#54
b11 M
0+
#55
1+
#56
b100 Q
1"
b100 M
0+
#57
1+
#58
1%
z"
bz !
bz 2
bz >
bz S
bz '
bz <
bz I
bz T
b0 Q
b101 M
b100 6
b100 H
b100 R
b100 U
0+
#59
1+
#60
z%
0$
0J
b1 Q
18
b0 6
b0 H
b0 R
b0 U
b0 M
b1 L
0+
#61
1+
#62
0J
b1 6
b1 H
b1 R
b1 U
0+
#63
bz X
bz W
1+
#64
b11 Q
0"
b0 '
b0 <
b0 I
b0 T
b10 !
b10 2
b10 >
b10 S
1J
08
0+
#65
b0 X
b10 W
1+
#66
0%
b100 '
b100 <
b100 I
b100 T
b10111011101110111101111110111011 !
b10111011101110111101111110111011 2
b10111011101110111101111110111011 >
b10111011101110111101111110111011 S
b11 6
b11 H
b11 R
b11 U
0+
#67
1+
#68
b1 M
0+
#69
1+
#70
b10 M
0+
#71
1+
#72
b11 M
0+
#73
1+
#74
1$
b100 Q
1"
b100 M
0+
#75
1+
#76
1%
z"
bz !
bz 2
bz >
bz S
bz '
bz <
bz I
bz T
b0 Q
b100 6
b100 H
b100 R
b100 U
b101 M
0+
#77
1+
#78
z%
0J
b0 M
b0 L
18
b0 6
b0 H
b0 R
b0 U
0+
