controller2/state_machine.v
module State_Machine(
    frame, irdy, trdy, devsel, state, clk, force_req, req, gnt, fcount, fend_count, freq_pending, ffinished
);

input wire frame, irdy, trdy, devsel, clk, force_req, req, gnt;
output reg[2:0] state;
reg[2:0] next_state;

parameter[2:0] 
idle=0, address=1, data_wait=2, data=3, final_data=4, finish=5;

output reg fcount, fend_count, freq_pending, ffinished, fgnt;

always @(negedge clk) begin
    state <= next_state;
    if (force_req) begin
        fend_count <= 0;
        fcount <= 1; 
    end
    if (!force_req && fcount) begin
        fcount <= 0;
        fend_count <= 1; 
    end
    if (!req && gnt) begin
        fgnt <= 0;
        freq_pending <= 1; 
    end
    if (req) begin
        freq_pending <= 0; 
    end
    if (state == address) begin
        freq_pending <= 0;
        ffinished <= 0; 
    end
    if (state == finish) begin
        ffinished <= 1; 
    end
    if (!gnt) begin
        fgnt <= 1; 
    end
end

always @(*) begin
    case (state)

        idle: if (fgnt) begin
            next_state = address;
        end

        address: if (!frame) begin
            next_state = data_wait; 
        end

        data_wait: if (!frame && !irdy && !trdy) begin
            next_state = data; 
        end
        else if (frame && !irdy && !trdy) begin
            next_state = finish; 
        end

        data: if (frame && !irdy && !trdy) begin
            next_state = finish; 
        end 
        else if (!frame && (irdy || trdy)) begin
            next_state = data_wait; 
        end

        // final_data: if (!irdy && !trdy) begin
        //     next_state = finish; 
        // end

        finish: next_state = idle;

        default: next_state = idle; //for initializing
    endcase
end

endmodule // State_Machine

controller2/initiator.v
module Initiator_Controller(
    input [1:0]devaddress, input [3:0] BE, /*output [31:0]data,*/ input force_req, input rd_wr, //force_req active high
    input clk, inout[31:0] AD, output[3:0] C_BE, input devsel, output frame, output irdy, input trdy,
    input gnt, output req);




// wire frame, irdy;
always @ (negedge clk) begin
    // frame <= frame;
    // irdy <= irdy;
    if (force_req) begin
        memory[7] <= devaddress;
    end
end

wire [2:0] state;
State_Machine sm (frame, irdy, trdy, devsel, state, clk, force_req, req, gnt, fcount, fend_count, freq_pending, ffinished);
parameter[2:0]
idle=0, address=1, data_wait=2, data=3, final_data=4, finish=5;

/*************************** count number of required transactions by master ******************************/
/* frame must not get asserted before force_req signal gets deasserted */
reg [1:0] counter;
always @ (negedge clk) begin
    if(fcount) begin     
        counter = counter + 1; 
    end
    if (state == data) begin
        counter = counter - 1; 
    end
end
always @ (posedge force_req) begin
    counter <= 0;
end

////////////////////////////////////* send request to arbiter *////////////////////////////////////////////////
reg bus_is_mine;    // indicate whether the bus is in this controller's command (active high)
assign req = ((fend_count && counter) && (~bus_is_mine)) ? 0 : 1; // MUST REVIEW
always @ (*) begin
    if (fcount) begin
        bus_is_mine = 0; 
    end
    if (state == address) begin
        bus_is_mine = 1; 
    end
    if (bus_is_mine && ffinished) begin
        bus_is_mine = 0; 
    end
end

////////////////////////////////////////////* set frame *////////////////////////////////////////////////////
assign frame = (bus_is_mine && state != finish) ? ( (state == address || counter > 1) ? 0 : 1) : 1'bz;

///////////////////////////////////////////* set AD with address *//////////////////////////////////////////
assign AD = (state == address && bus_is_mine) ? memory[7] : 32'hZZZZZZZZ;

////////////////////////////////////////////* set irdy *////////////////////////////////////////////////////
assign irdy = (bus_is_mine && (state == data_wait || state == data)) ? 0 : ( (bus_is_mine && state == finish) ? 1 : 1'bz );

////////////////////////////////////////////* read data *////////////////////////////////////////////////////
 //for storing entry
reg[2:0] mp;            //memory pointer
reg[31:0] memory[7:0];
wire[31:0] mem1, mem2, mem3, mem4;
assign mem1 = memory[0];
assign mem2 = memory[1];
assign mem3 = memory[2];
assign mem4 = memory[3];

always @ (posedge clk) begin
    if (bus_is_mine && (state == data)) begin
        memory[mp] <= AD;
        //mp++;   // illegal // unsynthesizable // accessing memory location mp while changing mp value
    end
    if (state == idle) begin
        mp <= 0; 
    end
end
always @ (negedge clk) begin    // increment memory pointer
    if (bus_is_mine && (state == data)) begin
        mp <= mp + 1; 
    end
end

endmodule

controller2/initiator_tb.v
module test;
    reg[1:0] address;
    wire[31:0] dat;
    reg[3:0] BE;
    wire[3:0] C_BE;
    reg force_req, clk, devsel, trdy, gnt, rd_wr;
    wire frame, irdy, req;
    reg[31:0] AD;
    wire[31:0] d;
    assign d = AD;
    initial begin
        AD = 32'hZZZZZZZZ;
        $dumpfile("test.vcd");
        $dumpvars(0,test);
        trdy = 1; devsel = 1; gnt = 1; force_req = 0;
        clk = 0;
        #4
        force_req = 1;
        address = 2'b01;
        #6
        force_req = 0;
        address = 2'bzz;
        #2
        gnt = 0;
        #2
        gnt = 1;
        #4
        trdy = 0;
        devsel = 0;
        AD = 32'hAAAAAAAA;
        #2
        AD = 32'hBBBBBBBB;

        # 10 $finish;
    end

    always #1 clk = ~clk;

    Initiator_Controller device( address,  BE,  force_req,  rd_wr, //force_req active high
     clk,  d,  C_BE,  devsel,  frame,  irdy,  trdy,
     gnt,  req);

endmodule //

controller2/test.vcd
$date
	Sat Dec 22 23:00:56 2018
$end
$version
	Icarus Verilog
$end
$timescale
	1s
$end
$scope module test $end
$var wire 4 ! C_BE [3:0] $end
$var wire 32 " d [31:0] $end
$var wire 1 # req $end
$var wire 1 $ irdy $end
$var wire 1 % frame $end
$var reg 32 & AD [31:0] $end
$var reg 4 ' BE [3:0] $end
$var reg 2 ( address [1:0] $end
$var reg 1 ) clk $end
$var reg 1 * devsel $end
$var reg 1 + force_req $end
$var reg 1 , gnt $end
$var reg 1 - rd_wr $end
$var reg 1 . trdy $end
$scope module device $end
$var wire 32 / AD [31:0] $end
$var wire 4 0 BE [3:0] $end
$var wire 4 1 C_BE [3:0] $end
$var wire 1 ) clk $end
$var wire 2 2 devaddress [1:0] $end
$var wire 1 * devsel $end
$var wire 1 + force_req $end
$var wire 1 , gnt $end
$var wire 32 3 mem1 [31:0] $end
$var wire 32 4 mem2 [31:0] $end
$var wire 32 5 mem3 [31:0] $end
$var wire 32 6 mem4 [31:0] $end
$var wire 1 - rd_wr $end
$var wire 1 . trdy $end
$var wire 3 7 state [2:0] $end
$var wire 1 # req $end
$var wire 1 $ irdy $end
$var wire 1 8 freq_pending $end
$var wire 1 % frame $end
$var wire 1 9 ffinished $end
$var wire 1 : fend_count $end
$var wire 1 ; fcount $end
$var reg 1 < bus_is_mine $end
$var reg 2 = counter [1:0] $end
$var reg 3 > mp [2:0] $end
$scope module sm $end
$var wire 1 ) clk $end
$var wire 1 * devsel $end
$var wire 1 + force_req $end
$var wire 1 % frame $end
$var wire 1 , gnt $end
$var wire 1 $ irdy $end
$var wire 1 # req $end
$var wire 1 . trdy $end
$var reg 1 ; fcount $end
$var reg 1 : fend_count $end
$var reg 1 9 ffinished $end
$var reg 1 ? fgnt $end
$var reg 1 8 freq_pending $end
$var reg 3 @ next_state [2:0] $end
$var reg 3 A state [2:0] $end
$upscope $end
$upscope $end
$upscope $end
$enddefinitions $end
#0
$dumpvars
b0 A
b0 @
x?
bx >
bx =
x<
x;
x:
x9
x8
b0 7
bx 6
bx 5
bx 4
bx 3
bx 2
bz 1
bx 0
bz /
1.
x-
1,
0+
1*
0)
bx (
bx '
bz &
x%
z$
x#
bz "
bz !
$end
#1
b0 >
1)
#2
0)
#3
1)
#4
1#
z%
0<
1;
0:
b0 =
0)
b1 (
b1 2
1+
#5
1)
#6
08
b1 =
0)
#7
1)
#8
b10 =
0)
#9
1)
#10
0#
1:
0;
b11 =
0)
bz (
bz 2
0+
#11
1)
#12
b1 @
1?
0)
0,
#13
1)
#14
b10 @
1#
0%
b1 "
b1 /
1<
18
0?
b1 7
b1 A
0)
1,
#15
1)
#16
0$
bz "
bz /
09
08
b10 7
b10 A
0)
#17
1)
#18
b11 7
b11 A
b11 @
0)
b10101010101010101010101010101010 "
b10101010101010101010101010101010 /
b10101010101010101010101010101010 &
0*
0.
#19
b10101010101010101010101010101010 3
1)
#20
b1 >
b10 =
0)
b10111011101110111011101110111011 "
b10111011101110111011101110111011 /
b10111011101110111011101110111011 &
#21
b10111011101110111011101110111011 4
1)
#22
b10 >
b101 @
1%
b1 =
0)
#23
b10111011101110111011101110111011 5
1)
#24
1$
z%
b0 @
b101 7
b101 A
b11 >
b0 =
0)
#25
1)
#26
z$
0<
19
b0 7
b0 A
0)
#27
b0 >
1)
