controller2/target.v
module Target_Controller(
    input clk, inout[31:0] AD, input[3:0] C_BE, output devsel, output trdy, input[2:0] state, input fvalid
    );

parameter[2:0] idle=0, address=1, data_wait=2, data=3, finish=5;
parameter[31:0] devaddress = 1;
reg[31:0] add;
reg[31:0] memory[7:0];
always @ (posedge clk) begin
    if (state == address) begin
        add <= AD; 
    end
end

assign devsel = (state == data && add == devaddress) ? 0 : (state == finish) ? 1 : 1'bz;
assign trdy = (state == data && add == devaddress) ? 0 : (state == finish) ? 1 : 1'bz;
assign AD = (state == data && add == devaddress) ?  32'hAAAAAAAA: 32'hZZZZZZZZ;

endmodule   //target read module

controller2/initiator.v
module Initiator_Controller(
    input [1:0]devaddress, input [3:0] BE, input force_req, input rd_wr, //force_req active high
    input clk, inout[31:0] AD, output[3:0] C_BE, output frame, output irdy,
    output req,
    input[2:0] state, input fcount, input fend_count, input freq_pending, input ffinished, input fvalid
    );

always @ (negedge clk) begin
    if (force_req) begin
        memory[7] <= devaddress;
    end
end

parameter[2:0]
idle=0, address=1, turnaround=2, data=3, finish=4;

/*************************** count number of required transactions by master ******************************/
/* frame must not get asserted before force_req signal gets deasserted */
reg [1:0] counter;
always @ (negedge clk) begin
    if(fcount) begin     
        counter = counter + 1; 
    end
    if (state == data) begin
        counter = counter - 1; 
    end
end
always @ (posedge force_req) begin
    counter <= 0;
end

////////////////////////////////////* send request to arbiter *////////////////////////////////////////////////
reg bus_is_mine;    // indicate whether the bus is in this controller's command (active high)
assign req = ((fend_count && counter) && (~bus_is_mine)) ? 0 : 1; // MUST REVIEW
always @ (*) begin
    if (fcount) begin
        bus_is_mine = 0; 
    end
    if (state == address) begin
        bus_is_mine = 1; 
    end
    if (bus_is_mine && ffinished) begin
        bus_is_mine = 0; 
    end
end

////////////////////////////////////////////* set frame *////////////////////////////////////////////////////
assign frame = (bus_is_mine && state != finish) ? ( (state == address || counter > 1) ? 0 : 1) : 1'bz;

///////////////////////////////////////////* set AD with address *//////////////////////////////////////////
assign AD = (state == address && bus_is_mine) ? memory[7] : 32'hZZZZZZZZ;

////////////////////////////////////////////* set irdy *////////////////////////////////////////////////////
assign irdy = (bus_is_mine && (state == turnaround || state == data)) ? 0 : ( (bus_is_mine && state == finish) ? 1 : 1'bz );

////////////////////////////////////////////* read data *////////////////////////////////////////////////////
 //for storing entry
reg[2:0] mp;            //memory pointer
reg[31:0] memory[7:0];
wire[31:0] mem1, mem2, mem3, mem4;
assign mem1 = memory[0];
assign mem2 = memory[1];
assign mem3 = memory[2];
assign mem4 = memory[3];

always @ (posedge clk) begin
    if (bus_is_mine && (state == data && fvalid)) begin
        memory[mp] <= AD;
    end
    if (state == idle) begin
        mp <= 0; 
    end
end
always @ (negedge clk) begin    // increment memory pointer
    if (bus_is_mine && (state == data && fvalid)) begin
        mp <= mp + 1; 
    end
end

endmodule   //master read module

controller2/state_machine2.v
module State_Machine(
    frame, irdy, trdy, devsel, state, clk, force_req, req, gnt, rd_wr, fcount, fend_count, freq_pending, ffinished, fvalid
);

/*
    This state machine is valid for both read and write transactions
    for read: rd_wr = 1
    for write: rd_wr = 0
*/

input wire frame, irdy, trdy, devsel, clk, force_req, req, gnt, rd_wr;
output reg[2:0] state;
reg[2:0] next_state;

parameter[2:0] 
/*
There are five states:
1. idle: here the bus is free (with respect to the device)
2. address: the initiator has asserted the frame and put a valid address on AD lines
3. turnaround: in case of read transaction the target must wait for two cylces after the frame being asserted
    to put valid data on AD and hence assert trdy
4. data: here data tranfers may occur depending on irdy & trdy (fvalid flag)
5. finish: all required transfers have occured and turnaround cycle ouccurs 
*/
idle=0, address=1, turnaround=2, data=3, finish=4;

output reg          //flags that contributes in synchronization of bus lines
    fcount,         //indicates assertion of force_req signal
    fend_count,     //indicates deassertion of force_req signal
    freq_pending,   //indicates a pending req signal
    ffinished,      //indicates finished transaction and free bus
    fvalid;         //indicates that a valid data transfer may occur next positive edge of clock
reg fgnt;           //indicates a granted bus ownership

always @(negedge clk) begin
    state <= next_state;
    if (force_req) begin
        fend_count <= 0;
        fcount <= 1; 
    end
    if (!force_req && fcount) begin
        fcount <= 0;
        fend_count <= 1; 
    end
    if (!req && gnt) begin
        fgnt <= 0;
        freq_pending <= 1; 
    end
    if (req) begin
        freq_pending <= 0; 
    end
    if (state == address) begin
        freq_pending <= 0;
        ffinished <= 0; 
    end
    if (state == finish) begin
        ffinished <= 1; 
    end
    if (!gnt) begin
        fgnt <= 1; 
    end
end

always @(*) begin
    case (state)

        idle: if (fgnt) begin
            next_state = address;
        end

        address: if (!frame) begin
            if (rd_wr) begin
                next_state = turnaround;               
            end
            else begin
                next_state = data;
            end
        end

        turnaround: begin
            next_state = data;
        end

        data: begin
        if (frame) begin
            next_state = finish; 
        end
        if(!trdy && !irdy) begin
            fvalid = 1; 
        end else begin
            fvalid = 0; 
        end
        end

        finish: begin next_state = idle; end

        default: next_state = idle; //for initializing
    endcase
end

endmodule // State_Machine

controller2/device.v
module Controller(
    input [1:0]devaddress, input [3:0] BE, input force_req, input rd_wr, //force_req active high
    input clk, inout[31:0] AD, inout[3:0] C_BE, inout devsel, inout frame, inout irdy, inout trdy,
    input gnt, output req
);

wire[2:0] state;

State_Machine sm(
    frame, irdy, trdy, devsel, state, clk, force_req, req, gnt, rd_wr, fcount, fend_count, freq_pending, ffinished, fvalid
);

Initiator_Controller ic(
    devaddress, BE, force_req, rd_wr, clk, AD, C_BE, frame, irdy, req, 
    state, fcount, fend_count, freq_pending, ffinished, fvalid
);

Target_Controller tc(
    clk, AD, C_BE, devsel, trdy, state, fvalid
);


endmodule

controller2/initiator_tb.v
`timescale 1us/1us
module test;
    reg[1:0] address;
    wire[31:0] dat;
    reg[3:0] BE;
    wire[3:0] C_BE;
    reg force_req, clk, gnt, rd_wr;
    wire frame, irdy, req;
    wire[31:0] d;
    initial begin
        $dumpfile("test.vcd");
        $dumpvars(0,test);
        gnt = 1; force_req = 0; rd_wr = 1;
        clk = 0;
        #4
        force_req = 1;
        address = 2'b01;
        #6
        force_req = 0;
        address = 2'bzz;
        #2
        gnt = 0;
        #2
        gnt = 1;
        
        # 30 $finish;
    end

    always #1 clk = ~clk;

    Controller device( address,  BE,  force_req,  rd_wr, //force_req active high
     clk,  d,  C_BE,  devsel,  frame,  irdy,  trdy,
     gnt,  req);

endmodule //

controller2/test.vcd
$date
	Sun Dec 23 16:44:42 2018
$end
$version
	Icarus Verilog
$end
$timescale
	1us
$end
$scope module test $end
$var wire 4 ! C_BE [3:0] $end
$var wire 32 " d [31:0] $end
$var wire 1 # trdy $end
$var wire 1 $ req $end
$var wire 1 % irdy $end
$var wire 1 & frame $end
$var wire 1 ' devsel $end
$var reg 4 ( BE [3:0] $end
$var reg 2 ) address [1:0] $end
$var reg 1 * clk $end
$var reg 1 + force_req $end
$var reg 1 , gnt $end
$var reg 1 - rd_wr $end
$scope module device $end
$var wire 32 . AD [31:0] $end
$var wire 4 / BE [3:0] $end
$var wire 4 0 C_BE [3:0] $end
$var wire 1 * clk $end
$var wire 2 1 devaddress [1:0] $end
$var wire 1 + force_req $end
$var wire 1 , gnt $end
$var wire 1 - rd_wr $end
$var wire 1 # trdy $end
$var wire 3 2 state [2:0] $end
$var wire 1 $ req $end
$var wire 1 % irdy $end
$var wire 1 3 fvalid $end
$var wire 1 4 freq_pending $end
$var wire 1 & frame $end
$var wire 1 5 ffinished $end
$var wire 1 6 fend_count $end
$var wire 1 7 fcount $end
$var wire 1 ' devsel $end
$scope module ic $end
$var wire 32 8 AD [31:0] $end
$var wire 4 9 BE [3:0] $end
$var wire 4 : C_BE [3:0] $end
$var wire 1 * clk $end
$var wire 2 ; devaddress [1:0] $end
$var wire 1 + force_req $end
$var wire 32 < mem1 [31:0] $end
$var wire 32 = mem2 [31:0] $end
$var wire 32 > mem3 [31:0] $end
$var wire 32 ? mem4 [31:0] $end
$var wire 1 - rd_wr $end
$var wire 3 @ state [2:0] $end
$var wire 1 $ req $end
$var wire 1 % irdy $end
$var wire 1 3 fvalid $end
$var wire 1 4 freq_pending $end
$var wire 1 & frame $end
$var wire 1 5 ffinished $end
$var wire 1 6 fend_count $end
$var wire 1 7 fcount $end
$var reg 1 A bus_is_mine $end
$var reg 2 B counter [1:0] $end
$var reg 3 C mp [2:0] $end
$upscope $end
$scope module sm $end
$var wire 1 * clk $end
$var wire 1 + force_req $end
$var wire 1 & frame $end
$var wire 1 , gnt $end
$var wire 1 % irdy $end
$var wire 1 - rd_wr $end
$var wire 1 $ req $end
$var wire 1 # trdy $end
$var wire 1 ' devsel $end
$var reg 1 7 fcount $end
$var reg 1 6 fend_count $end
$var reg 1 5 ffinished $end
$var reg 1 D fgnt $end
$var reg 1 4 freq_pending $end
$var reg 1 3 fvalid $end
$var reg 3 E next_state [2:0] $end
$var reg 3 F state [2:0] $end
$upscope $end
$scope module tc $end
$var wire 32 G AD [31:0] $end
$var wire 4 H C_BE [3:0] $end
$var wire 1 * clk $end
$var wire 1 3 fvalid $end
$var wire 3 I state [2:0] $end
$var wire 1 # trdy $end
$var wire 1 ' devsel $end
$var reg 32 J add [31:0] $end
$upscope $end
$upscope $end
$upscope $end
$enddefinitions $end
#0
$dumpvars
bx J
b0 I
bz H
bz G
b0 F
b0 E
xD
bx C
bx B
xA
b0 @
bx ?
bx >
bx =
bx <
bx ;
bz :
bx 9
bz 8
x7
x6
x5
x4
x3
b0 2
bx 1
bz 0
bx /
bz .
1-
1,
0+
0*
bx )
bx (
z'
x&
z%
x$
z#
bz "
bz !
$end
#1
b0 C
1*
#2
0*
#3
1*
#4
1$
z&
0A
17
06
b0 B
0*
b1 )
b1 1
b1 ;
1+
#5
1*
#6
04
b1 B
0*
#7
1*
#8
b10 B
0*
#9
1*
#10
0$
16
07
b11 B
0*
bz )
bz 1
bz ;
0+
#11
1*
#12
b1 E
1D
0*
0,
#13
1*
#14
b10 E
1$
0&
b1 "
b1 .
b1 8
b1 G
1A
14
0D
b1 2
b1 @
b1 F
b1 I
0*
1,
#15
b1 J
1*
#16
0%
bz "
bz .
bz 8
bz G
b11 E
05
04
b10 2
b10 @
b10 F
b10 I
0*
#17
1*
#18
0'
0#
b10101010101010101010101010101010 "
b10101010101010101010101010101010 .
b10101010101010101010101010101010 8
b10101010101010101010101010101010 G
13
b11 2
b11 @
b11 F
b11 I
0*
#19
b10101010101010101010101010101010 <
1*
#20
b1 C
b10 B
0*
#21
b10101010101010101010101010101010 =
1*
#22
b10 C
b100 E
1&
b1 B
0*
#23
b10101010101010101010101010101010 >
1*
#24
1%
z'
z#
z&
bz "
bz .
bz 8
bz G
b0 E
b100 2
b100 @
b100 F
b100 I
b11 C
b0 B
0*
#25
1*
#26
z%
0A
15
b0 2
b0 @
b0 F
b0 I
0*
#27
b0 C
1*
