arbitration/arbiter.v
module arbiter(gnt,req,clk
);
reg [3:0] wgnt;
input clk;

input[3:0] req;

output reg[3:0] gnt;

always @(posedge clk) begin
if(req[0]==0)
begin
wgnt<=4'b1110;
end
else if (req[1]==0)
begin
wgnt<=4'b1101;
end
else if (req[2]==0)
begin
wgnt<=4'b1011;
end
else if (req[3]==0)
begin
wgnt<=4'b0111;
end
else begin
wgnt<=4'b1111;
end
end
always @(negedge clk) begin
gnt <=wgnt;
end
endmodule

device/target.v
module Target_Controller(
    input clk, inout[31:0] AD, input[3:0] C_BE, output devsel, output trdy, input[2:0] state, input fvalid, input[1:0] tar_address, input frame
    );

parameter[3:0]
/* Command value for read = 1, write = 0 */
read = 1, write = 0;

parameter[2:0] idle=0, address=1, turnaround=2, data=3, finish=4;
reg[31:0] add;
reg[31:0] memory[0:9];
reg[3:0] mp;
wire[31:0] mem1; assign mem1 = memory[0];
wire[31:0] mem2; assign mem2 = memory[1];    
wire[31:0] mem3; assign mem3 = memory[2];
wire[31:0] mem4; assign mem4 = memory[3];
reg[3:0] command;
always @ (posedge clk) begin
    if (!frame && state == idle) begin
        add <= AD;
        command <= C_BE; 
        mp <= 0;
    end
    if(state == data && fvalid && add === tar_address) begin
        if(C_BE[0]) begin
            memory[mp][7:0] <= AD[7:0]; 
        end
        if(C_BE[1]) begin
            memory[mp][15:8] <= AD[15:8];  
        end
        if(C_BE[2]) begin
            memory[mp][23:16] <= AD[23:16];  
        end
        if(C_BE[3]) begin
            memory[mp][31:24] <= AD[31:24];  
        end
    end
    if(state == finish) begin
        add <= 32'hZZZZZZZZ;
    end
end
always @ (negedge clk) begin
    if (state == data && command == write && fvalid && add === tar_address) begin
        mp <= mp + 1; 
    end
end

assign devsel = (state == data && add === tar_address) ? 0 : ((state == finish || state == turnaround || !frame) && add === tar_address) ? 1 : 1'bz;
assign trdy = (state == data && add === tar_address) ? 0 : ((state == finish || state == turnaround || !frame) && add === tar_address) ? 1 : 1'bz;
assign AD = (state == data && add === tar_address && command == read) ?  memory[mp]: 32'hZZZZZZZZ;

endmodule   //target read module

device/initiator.v
module Initiator_Controller(
    input [1:0]devaddress, input[3:0] BE, input force_req, input rd_wr, input[31:0] write_data,
    input clk, inout[31:0] AD, output[3:0] C_BE, output frame, output irdy,
    output req,
    input[2:0] state, input fcount, input fend_count, input ffinished, input fvalid, input bus_is_mine,
    input fburst    // extra input for burst transactions (active high)
    );

/*
  **When in burst mode the intiator continues in data phases until either maximum failed transfers 
    or fburst signalis deasserted.
  **In Normal mode the intiator completes one data transfer and continues to the next transaction.
*/

reg[3:0] command[0:3];
wire[3:0] comm;
assign comm = command[0];
/*
    when force_req signal is asserted, at every positive edge a corresponding target-address and command is saved
    in internal memory  
*/
always @ (posedge clk) begin
    if (fcount) begin
        memory[9 - counter] <= devaddress;
        command[counter] <= rd_wr;
    end
end

parameter[2:0]    
idle=0, address=3'b001, turnaround=3'b010, data=3'b011, finish=3'b100;  //states are declared in State_Machine module

/*************************** count number of required transactions by master ******************************/
            /* frame shall not get asserted before force_req signal gets deasserted */

reg[2:0] failed_counter;        //count the cycles at which the target hasn't responded ** max limit 5 cycles
reg [1:0] counter, max;         //counts and saves the number of required transactions
always @ (negedge clk) begin
    if(fcount) begin     
        counter <= counter + 1; 
        max <= counter + 1;
        failed_counter <= 0;
    end
    if (state == finish && (!fburst || failed_counter > 4) && bus_is_mine) begin
        counter <= counter - 1; 
        failed_counter <= 0;
    end
    if ((state == data || state == turnaround) && !fvalid && fburst) begin
        failed_counter <= failed_counter + 1;
    end
    if (state == data && fvalid) begin
        failed_counter <= 0;
    end
end
always @ (posedge force_req) begin
    counter <= 0;
    max <= 0;  
    mp <= 0;
end

////////////////////////////////////* send request to arbiter *////////////////////////////////////////////////
assign req = (fend_count === 1 && 
                ((counter && 
                (!bus_is_mine || (bus_is_mine && state == idle) || (bus_is_mine && fburst && failed_counter < 4))
                || counter > 1))) ? 0 : 1; // MUST REVIEW

////////////////////////////////////////////* set frame *////////////////////////////////////////////////////
assign frame = (bus_is_mine === 1 && state != finish && counter) ?
 ( (state == address || ( (state == data || state == turnaround ) && (fburst && (failed_counter < 4) ) ) ) ? 0 : 1) : 1'bz;  //multi transactions 

///////////////////////////////////////////* set AD with address *//////////////////////////////////////////
assign AD = (state == address && bus_is_mine === 1) ? memory[9 - max + counter] : (bus_is_mine && command[max-counter] === 0 && state === data) ? write_data : 32'hZZZZZZZZ;
assign C_BE = (state == address && bus_is_mine === 1) ? command[max - counter] : ( (state === data && bus_is_mine) ? BE : 4'bzzzz );

////////////////////////////////////////////* set irdy *////////////////////////////////////////////////////
assign irdy = (bus_is_mine === 1 && (state == turnaround || state == data)) ? 0 : ( (bus_is_mine === 1 && (state == finish || state == address) ) ? 1 : 1'bz );

////////////////////////////////////////////* read data *////////////////////////////////////////////////////
                            /* read data is saved in this internal memory */

reg[2:0] mp;            //memory pointer
reg[31:0] memory[9:0];  //multi transaction 
wire[31:0] mem1, mem2, mem3, mem4, mem9, mem10;
assign mem1 = memory[0];
assign mem2 = memory[1];
assign mem3 = memory[2];
assign mem4 = memory[3];
assign mem9 = memory[8];
assign mem10 = memory[9];

always @ (posedge clk) begin
    if (bus_is_mine && (state == data && fvalid) && command[max-counter] == 1) begin
        memory[mp] <= AD;
    end
    if (state == idle && counter == 0) begin
        mp <= 0; 
    end
    if (fcount) begin
        memory[9-mp] <= devaddress; 
    end

end
always @ (negedge clk) begin    // increment memory pointer
    if (bus_is_mine && (state == data && fvalid) && mp < 8 && command[max-counter] == 1) begin
        mp <= mp + 1; 
    end
    if (fcount) begin
        mp <= mp + 1; 
    end
    if (state == address) begin
        mp <= 0; 
    end
end

endmodule   //master read & write module

device/state_machine.v
module State_Machine(
    frame, irdy, trdy, devsel, state, clk, force_req, burst, req, gnt, rd_wr, fcount, fend_count, ffinished, fvalid, fburst, bus_is_mine
);

/*
    This state machine is valid for both read and write transactions
    for read: rd_wr = 1
    for write: rd_wr = 0
*/

input wire frame, irdy, trdy, devsel, clk, force_req, burst, req, gnt, rd_wr;
output reg[2:0] state;
reg[2:0] next_state;

parameter[2:0] 
/*
There are five states:
1. idle: here the bus is free (with respect to the device)
2. address: the initiator has asserted the frame and put a valid address on AD lines
3. turnaround: in case of read transaction the target must wait for two cylces after the frame being asserted
    to put valid data on AD and hence assert trdy
4. data: here data tranfers may occur depending on irdy & trdy (fvalid flag)
5. finish: all required transfers have occured and turnaround cycle ouccurs 
*/
idle=0, address=1, turnaround=2, data=3, finish=4;

output reg          //flags that contributes in synchronization of bus lines
    fcount,         //indicates assertion of force_req signal
    fend_count,     //indicates deassertion of force_req signal
    ffinished,      //indicates finished transaction and free bus
    fvalid,         //indicates that a valid data transfer may occur next positive edge of clock **combinational
    fburst,
    bus_is_mine;
reg fgnt;           //indicates a granted bus ownership

always @(negedge clk) begin
    state <= next_state;      
    if (force_req) begin
        fend_count <= 0;
        fcount <= 1; 
    end
    if (!force_req && fcount) begin
        fcount <= 0;
        fend_count <= 1;
    end
    if (state == address) begin
        ffinished <= 0; 
    end
    if (state == finish) begin
        ffinished <= 1;
    end
    if (!gnt) begin
        fgnt <= 1; 
    end else begin
        fgnt <= 0; 
    end
    if (burst) begin
        fburst <= 1; 
    end else begin
        fburst <= 0; 
    end
end

always @(posedge clk) begin
    case (state)

        idle: begin
            fvalid = 1;
            bus_is_mine = 0 ;
            if (fgnt && !req) begin
                next_state = address;
                bus_is_mine = 1;
            end
            if (fgnt && !req && !frame) begin
                bus_is_mine = 0;
            end
            if (!frame && !bus_is_mine) begin
                if (rd_wr) begin
                    next_state = turnaround;               
                end
                else begin
                    next_state = data;
                end
            end
        end

        address: begin
            if (!frame) begin
                if (rd_wr) begin
                    next_state = turnaround;               
                end
                else begin
                    next_state = data;
                end
            end
            fvalid = 1;
        end

        turnaround: begin
            fvalid = 1;
            next_state = data;
        end

        data: begin
            if(fgnt === 0 && bus_is_mine) begin
                next_state = finish; 
            end
            if (frame) begin
                next_state = finish; 
            end
            if(trdy === 0 && irdy === 0 && devsel === 0) begin
                fvalid = 1; 
            end else begin
                fvalid = 0; 
            end
        end

        finish: begin 
            next_state = idle; 
        end

        default: next_state = idle; //for initializing
    endcase
end

endmodule // State_Machine

device/device.v
module Controller(
    input [1:0]devaddress, input [3:0] BE, input force_req, input rd_wr, input[31:0]  write_data, input burst,
    input clk, inout[31:0] AD, inout[3:0] C_BE, inout devsel, inout frame, inout irdy, inout trdy,
    input gnt, output req,
    input reset_address //active high
);

wire[2:0] state;
reg[1:0] tar_add;
always @ (reset_address) begin
    if (reset_address) begin
        tar_add <= devaddress;
    end
end

State_Machine sm(
    frame, irdy, trdy, devsel, state, clk, force_req, burst, req, gnt, C_BE[0], fcount, fend_count, ffinished, fvalid, fburst, bus_is_mine
);

Initiator_Controller ic(
    devaddress, BE, force_req, rd_wr, write_data, clk, AD, C_BE, frame, irdy, req, 
    state, fcount, fend_count, ffinished, fvalid, bus_is_mine, fburst
);

Target_Controller tc(
    clk, AD, C_BE, devsel, trdy, state, fvalid, tar_add, frame
);


endmodule

device/testbench2.v
`timescale 1us/1us
module test;

parameter A = 2'b00, B= 2'b01, C= 2'b10;
reg[1:0] addressA; reg[1:0] addressB; reg[1:0] addressC;
reg[31:0] datA; reg[31:0] datB; reg[31:0] datC;
reg[3:0] BE_A; reg[3:0] BE_B; reg[3:0] BE_C;
wire[3:0] C_BE;
wire[3:0] gnt;
assign gntA = gnt[1]; assign gntB = gnt[2]; assign gntC = gnt[3];
wire[3:0] req;
assign req = {reqC, reqB, reqA, 1'b1};
wire frame, irdy, reqA, reqB, reqC;
reg force_reqA, force_reqB, force_reqC, clk, rd_wrA, rd_wrB, rd_wrC, burstA, burstB, burstC, rframe, reset_add;
wire[31:0] d;
initial begin
    $dumpfile("test.vcd");
    $dumpvars(0,test);
    rframe = 1'bz;
    force_reqA = 0; force_reqB = 0; rd_wrA = 0; rd_wrB = 0;
    burstA = 0; burstB = 0; burstC = 0; reset_add = 1; addressA = A; addressB = B; addressC = C;
    clk = 0;
    #1
    reset_add = 0;
    force_reqA = 1;
    addressA = B;
    rd_wrA = 0;
    #2
    force_reqA = 0;
    burstA = 1;
    datA = 32'hAAAAAAAA;
    BE_A = 4'b1111;
    #12
    burstA = 0;
    
    force_reqB = 1;
    addressB = A;
    rd_wrB = 0;
    #2
    force_reqB = 0;
    burstB = 1;
    datB = 32'hBBBBBBBB;
    BE_B = 4'b1111;
    #10
    burstB = 0;

    force_reqC = 1;
    #2
    force_reqA = 1;
    addressA = C;
    BE_C = 4'b1111;
    addressC = A;
    rd_wrA = 0;
    rd_wrC = 0;
    #2
    force_reqA = 0;
    force_reqC = 0;    
    datC = 32'hCCCCCCCC;
    addressC = B;
    
    # 40 $finish;
end

always #1 clk = ~clk;

Controller deviceA( addressA,  BE_A,  force_reqA,  rd_wrA, datA, burstA,
    clk,  d,  C_BE,  devsel,  frame,  irdy,  trdy,
    gntA,  reqA,
    reset_add
    );

Controller deviceB( addressB,  BE_B,  force_reqB,  rd_wrB, datB, burstB,
    clk,  d,  C_BE,  devsel,  frame,  irdy,  trdy,
    gntB,  reqB,
    reset_add
    );

Controller deviceC( addressC,  BE_C,  force_reqC,  rd_wrC, datC, burstC,
    clk,  d,  C_BE,  devsel,  frame,  irdy,  trdy,
    gntC,  reqC,
    reset_add
    );

arbiter arbit(gnt, req, clk);


endmodule //

device/test.vcd
$date
	Thu Dec 27 11:31:31 2018
$end
$version
	Icarus Verilog
$end
$timescale
	1us
$end
$scope module test $end
$var wire 4 ! C_BE [3:0] $end
$var wire 32 " d [31:0] $end
$var wire 1 # devsel $end
$var wire 1 $ frame $end
$var wire 1 % irdy $end
$var wire 1 & trdy $end
$var wire 1 ' reqC $end
$var wire 1 ( reqB $end
$var wire 1 ) reqA $end
$var wire 4 * req [3:0] $end
$var wire 1 + gntC $end
$var wire 1 , gntB $end
$var wire 1 - gntA $end
$var wire 4 . gnt [3:0] $end
$var reg 4 / BE_A [3:0] $end
$var reg 4 0 BE_B [3:0] $end
$var reg 4 1 BE_C [3:0] $end
$var reg 2 2 addressA [1:0] $end
$var reg 2 3 addressB [1:0] $end
$var reg 2 4 addressC [1:0] $end
$var reg 1 5 burstA $end
$var reg 1 6 burstB $end
$var reg 1 7 burstC $end
$var reg 1 8 clk $end
$var reg 32 9 datA [31:0] $end
$var reg 32 : datB [31:0] $end
$var reg 32 ; datC [31:0] $end
$var reg 1 < force_reqA $end
$var reg 1 = force_reqB $end
$var reg 1 > force_reqC $end
$var reg 1 ? rd_wrA $end
$var reg 1 @ rd_wrB $end
$var reg 1 A rd_wrC $end
$var reg 1 B reset_add $end
$var reg 1 C rframe $end
$scope module arbit $end
$var wire 1 8 clk $end
$var wire 4 D req [3:0] $end
$var reg 4 E gnt [3:0] $end
$var reg 4 F wgnt [3:0] $end
$upscope $end
$scope module deviceA $end
$var wire 32 G AD [31:0] $end
$var wire 4 H BE [3:0] $end
$var wire 4 I C_BE [3:0] $end
$var wire 1 5 burst $end
$var wire 1 8 clk $end
$var wire 2 J devaddress [1:0] $end
$var wire 1 # devsel $end
$var wire 1 < force_req $end
$var wire 1 $ frame $end
$var wire 1 - gnt $end
$var wire 1 % irdy $end
$var wire 1 ? rd_wr $end
$var wire 1 B reset_address $end
$var wire 1 & trdy $end
$var wire 32 K write_data [31:0] $end
$var wire 3 L state [2:0] $end
$var wire 1 ) req $end
$var wire 1 M fvalid $end
$var wire 1 N ffinished $end
$var wire 1 O fend_count $end
$var wire 1 P fcount $end
$var wire 1 Q fburst $end
$var wire 1 R bus_is_mine $end
$var reg 2 S tar_add [1:0] $end
$scope module ic $end
$var wire 32 T AD [31:0] $end
$var wire 4 U BE [3:0] $end
$var wire 4 V C_BE [3:0] $end
$var wire 1 8 clk $end
$var wire 4 W comm [3:0] $end
$var wire 2 X devaddress [1:0] $end
$var wire 1 < force_req $end
$var wire 1 $ frame $end
$var wire 1 % irdy $end
$var wire 32 Y mem1 [31:0] $end
$var wire 32 Z mem10 [31:0] $end
$var wire 32 [ mem2 [31:0] $end
$var wire 32 \ mem3 [31:0] $end
$var wire 32 ] mem4 [31:0] $end
$var wire 32 ^ mem9 [31:0] $end
$var wire 1 ? rd_wr $end
$var wire 32 _ write_data [31:0] $end
$var wire 3 ` state [2:0] $end
$var wire 1 ) req $end
$var wire 1 M fvalid $end
$var wire 1 N ffinished $end
$var wire 1 O fend_count $end
$var wire 1 P fcount $end
$var wire 1 Q fburst $end
$var wire 1 R bus_is_mine $end
$var reg 2 a counter [1:0] $end
$var reg 3 b failed_counter [2:0] $end
$var reg 2 c max [1:0] $end
$var reg 3 d mp [2:0] $end
$upscope $end
$scope module sm $end
$var wire 1 5 burst $end
$var wire 1 8 clk $end
$var wire 1 # devsel $end
$var wire 1 < force_req $end
$var wire 1 $ frame $end
$var wire 1 - gnt $end
$var wire 1 % irdy $end
$var wire 1 e rd_wr $end
$var wire 1 ) req $end
$var wire 1 & trdy $end
$var reg 1 R bus_is_mine $end
$var reg 1 Q fburst $end
$var reg 1 P fcount $end
$var reg 1 O fend_count $end
$var reg 1 N ffinished $end
$var reg 1 f fgnt $end
$var reg 1 M fvalid $end
$var reg 3 g next_state [2:0] $end
$var reg 3 h state [2:0] $end
$upscope $end
$scope module tc $end
$var wire 32 i AD [31:0] $end
$var wire 4 j C_BE [3:0] $end
$var wire 1 8 clk $end
$var wire 1 # devsel $end
$var wire 1 $ frame $end
$var wire 1 M fvalid $end
$var wire 32 k mem1 [31:0] $end
$var wire 32 l mem2 [31:0] $end
$var wire 32 m mem3 [31:0] $end
$var wire 32 n mem4 [31:0] $end
$var wire 3 o state [2:0] $end
$var wire 2 p tar_address [1:0] $end
$var wire 1 & trdy $end
$var reg 32 q add [31:0] $end
$var reg 4 r command [3:0] $end
$var reg 4 s mp [3:0] $end
$upscope $end
$upscope $end
$scope module deviceB $end
$var wire 32 t AD [31:0] $end
$var wire 4 u BE [3:0] $end
$var wire 4 v C_BE [3:0] $end
$var wire 1 6 burst $end
$var wire 1 8 clk $end
$var wire 2 w devaddress [1:0] $end
$var wire 1 # devsel $end
$var wire 1 = force_req $end
$var wire 1 $ frame $end
$var wire 1 , gnt $end
$var wire 1 % irdy $end
$var wire 1 @ rd_wr $end
$var wire 1 B reset_address $end
$var wire 1 & trdy $end
$var wire 32 x write_data [31:0] $end
$var wire 3 y state [2:0] $end
$var wire 1 ( req $end
$var wire 1 z fvalid $end
$var wire 1 { ffinished $end
$var wire 1 | fend_count $end
$var wire 1 } fcount $end
$var wire 1 ~ fburst $end
$var wire 1 !" bus_is_mine $end
$var reg 2 "" tar_add [1:0] $end
$scope module ic $end
$var wire 32 #" AD [31:0] $end
$var wire 4 $" BE [3:0] $end
$var wire 4 %" C_BE [3:0] $end
$var wire 1 8 clk $end
$var wire 4 &" comm [3:0] $end
$var wire 2 '" devaddress [1:0] $end
$var wire 1 = force_req $end
$var wire 1 $ frame $end
$var wire 1 % irdy $end
$var wire 32 (" mem1 [31:0] $end
$var wire 32 )" mem10 [31:0] $end
$var wire 32 *" mem2 [31:0] $end
$var wire 32 +" mem3 [31:0] $end
$var wire 32 ," mem4 [31:0] $end
$var wire 32 -" mem9 [31:0] $end
$var wire 1 @ rd_wr $end
$var wire 32 ." write_data [31:0] $end
$var wire 3 /" state [2:0] $end
$var wire 1 ( req $end
$var wire 1 z fvalid $end
$var wire 1 { ffinished $end
$var wire 1 | fend_count $end
$var wire 1 } fcount $end
$var wire 1 ~ fburst $end
$var wire 1 !" bus_is_mine $end
$var reg 2 0" counter [1:0] $end
$var reg 3 1" failed_counter [2:0] $end
$var reg 2 2" max [1:0] $end
$var reg 3 3" mp [2:0] $end
$upscope $end
$scope module sm $end
$var wire 1 6 burst $end
$var wire 1 8 clk $end
$var wire 1 # devsel $end
$var wire 1 = force_req $end
$var wire 1 $ frame $end
$var wire 1 , gnt $end
$var wire 1 % irdy $end
$var wire 1 4" rd_wr $end
$var wire 1 ( req $end
$var wire 1 & trdy $end
$var reg 1 !" bus_is_mine $end
$var reg 1 ~ fburst $end
$var reg 1 } fcount $end
$var reg 1 | fend_count $end
$var reg 1 { ffinished $end
$var reg 1 5" fgnt $end
$var reg 1 z fvalid $end
$var reg 3 6" next_state [2:0] $end
$var reg 3 7" state [2:0] $end
$upscope $end
$scope module tc $end
$var wire 32 8" AD [31:0] $end
$var wire 4 9" C_BE [3:0] $end
$var wire 1 8 clk $end
$var wire 1 # devsel $end
$var wire 1 $ frame $end
$var wire 1 z fvalid $end
$var wire 32 :" mem1 [31:0] $end
$var wire 32 ;" mem2 [31:0] $end
$var wire 32 <" mem3 [31:0] $end
$var wire 32 =" mem4 [31:0] $end
$var wire 3 >" state [2:0] $end
$var wire 2 ?" tar_address [1:0] $end
$var wire 1 & trdy $end
$var reg 32 @" add [31:0] $end
$var reg 4 A" command [3:0] $end
$var reg 4 B" mp [3:0] $end
$upscope $end
$upscope $end
$scope module deviceC $end
$var wire 32 C" AD [31:0] $end
$var wire 4 D" BE [3:0] $end
$var wire 4 E" C_BE [3:0] $end
$var wire 1 7 burst $end
$var wire 1 8 clk $end
$var wire 2 F" devaddress [1:0] $end
$var wire 1 # devsel $end
$var wire 1 > force_req $end
$var wire 1 $ frame $end
$var wire 1 + gnt $end
$var wire 1 % irdy $end
$var wire 1 A rd_wr $end
$var wire 1 B reset_address $end
$var wire 1 & trdy $end
$var wire 32 G" write_data [31:0] $end
$var wire 3 H" state [2:0] $end
$var wire 1 ' req $end
$var wire 1 I" fvalid $end
$var wire 1 J" ffinished $end
$var wire 1 K" fend_count $end
$var wire 1 L" fcount $end
$var wire 1 M" fburst $end
$var wire 1 N" bus_is_mine $end
$var reg 2 O" tar_add [1:0] $end
$scope module ic $end
$var wire 32 P" AD [31:0] $end
$var wire 4 Q" BE [3:0] $end
$var wire 4 R" C_BE [3:0] $end
$var wire 1 8 clk $end
$var wire 4 S" comm [3:0] $end
$var wire 2 T" devaddress [1:0] $end
$var wire 1 > force_req $end
$var wire 1 $ frame $end
$var wire 1 % irdy $end
$var wire 32 U" mem1 [31:0] $end
$var wire 32 V" mem10 [31:0] $end
$var wire 32 W" mem2 [31:0] $end
$var wire 32 X" mem3 [31:0] $end
$var wire 32 Y" mem4 [31:0] $end
$var wire 32 Z" mem9 [31:0] $end
$var wire 1 A rd_wr $end
$var wire 32 [" write_data [31:0] $end
$var wire 3 \" state [2:0] $end
$var wire 1 ' req $end
$var wire 1 I" fvalid $end
$var wire 1 J" ffinished $end
$var wire 1 K" fend_count $end
$var wire 1 L" fcount $end
$var wire 1 M" fburst $end
$var wire 1 N" bus_is_mine $end
$var reg 2 ]" counter [1:0] $end
$var reg 3 ^" failed_counter [2:0] $end
$var reg 2 _" max [1:0] $end
$var reg 3 `" mp [2:0] $end
$upscope $end
$scope module sm $end
$var wire 1 7 burst $end
$var wire 1 8 clk $end
$var wire 1 # devsel $end
$var wire 1 > force_req $end
$var wire 1 $ frame $end
$var wire 1 + gnt $end
$var wire 1 % irdy $end
$var wire 1 a" rd_wr $end
$var wire 1 ' req $end
$var wire 1 & trdy $end
$var reg 1 N" bus_is_mine $end
$var reg 1 M" fburst $end
$var reg 1 L" fcount $end
$var reg 1 K" fend_count $end
$var reg 1 J" ffinished $end
$var reg 1 b" fgnt $end
$var reg 1 I" fvalid $end
$var reg 3 c" next_state [2:0] $end
$var reg 3 d" state [2:0] $end
$upscope $end
$scope module tc $end
$var wire 32 e" AD [31:0] $end
$var wire 4 f" C_BE [3:0] $end
$var wire 1 8 clk $end
$var wire 1 # devsel $end
$var wire 1 $ frame $end
$var wire 1 I" fvalid $end
$var wire 32 g" mem1 [31:0] $end
$var wire 32 h" mem2 [31:0] $end
$var wire 32 i" mem3 [31:0] $end
$var wire 32 j" mem4 [31:0] $end
$var wire 3 k" state [2:0] $end
$var wire 2 l" tar_address [1:0] $end
$var wire 1 & trdy $end
$var reg 32 m" add [31:0] $end
$var reg 4 n" command [3:0] $end
$var reg 4 o" mp [3:0] $end
$upscope $end
$upscope $end
$upscope $end
$enddefinitions $end
#0
$dumpvars
bx o"
bx n"
bx m"
b10 l"
bx k"
bx j"
bx i"
bx h"
bx g"
bz f"
bz e"
bx d"
bx c"
0b"
za"
bx `"
bx _"
bx ^"
bx ]"
bx \"
bx ["
bx Z"
bx Y"
bx X"
bx W"
bx V"
bx U"
b10 T"
bx S"
bz R"
bx Q"
bz P"
b10 O"
xN"
0M"
xL"
xK"
xJ"
xI"
bx H"
bx G"
b10 F"
bz E"
bx D"
bz C"
bx B"
bx A"
bx @"
b1 ?"
bx >"
bx ="
bx <"
bx ;"
bx :"
bz 9"
bz 8"
bx 7"
bx 6"
05"
z4"
bx 3"
bx 2"
bx 1"
bx 0"
bx /"
bx ."
bx -"
bx ,"
bx +"
bx *"
bx )"
bx ("
b1 '"
bx &"
bz %"
bx $"
bz #"
b1 ""
x!"
0~
x}
x|
x{
xz
bx y
bx x
b1 w
bz v
bx u
bz t
bx s
bx r
bx q
b0 p
bx o
bx n
bx m
bx l
bx k
bz j
bz i
bx h
bx g
0f
ze
bx d
bx c
bx b
bx a
bx `
bx _
bx ^
bx ]
bx \
bx [
bx Z
bx Y
b0 X
bx W
bz V
bx U
bz T
b0 S
xR
0Q
xP
xO
xN
xM
bx L
bx K
b0 J
bz I
bx H
bz G
bx F
bx E
b1111 D
zC
1B
xA
0@
0?
x>
0=
0<
bx ;
bx :
bx 9
08
07
06
05
b10 4
b1 3
b0 2
bx 1
bx 0
bx /
bx .
x-
x,
x+
b1111 *
1)
1(
1'
z&
z%
z$
z#
bz "
bz !
$end
#1
b1111 F
b0 d
b0 c
b0 a
b0 g
b0 6"
b0 c"
18
b1 2
b1 J
b1 X
1<
0B
#2
1+
1,
1-
b1111 .
b1111 E
b0 H"
b0 \"
b0 d"
b0 k"
b0 y
b0 /"
b0 7"
b0 >"
1P
0O
b0 L
b0 `
b0 h
b0 o
08
#3
b0 W
b1 Z
0N"
1I"
0!"
1z
0R
1M
18
b1111 /
b1111 H
b1111 U
b10101010101010101010101010101010 9
b10101010101010101010101010101010 K
b10101010101010101010101010101010 _
15
0<
#4
b1101 *
b1101 D
0)
1Q
1O
0P
b0 b
b1 c
b1 a
b1 d
08
#5
b1101 F
18
#6
0-
b1101 .
b1101 E
08
#7
18
#8
1f
08
#9
1$
1R
b1 g
18
#10
1%
0$
0e
04"
0a"
b0 !
b0 I
b0 V
b0 j
b0 v
b0 %"
b0 9"
b0 E"
b0 R"
b0 f"
b1 "
b1 G
b1 T
b1 i
b1 t
b1 #"
b1 8"
b1 C"
b1 P"
b1 e"
b1 L
b1 `
b1 h
b1 o
08
#11
1#
1&
b0 o"
b0 n"
b1 m"
b0 B"
b0 A"
b1 @"
b11 c"
b11 6"
b11 g
18
#12
0%
0$
1e
14"
1a"
0#
0&
b1111 !
b1111 I
b1111 V
b1111 j
b1111 v
b1111 %"
b1111 9"
b1111 E"
b1111 R"
b1111 f"
b10101010101010101010101010101010 "
b10101010101010101010101010101010 G
b10101010101010101010101010101010 T
b10101010101010101010101010101010 i
b10101010101010101010101010101010 t
b10101010101010101010101010101010 #"
b10101010101010101010101010101010 8"
b10101010101010101010101010101010 C"
b10101010101010101010101010101010 P"
b10101010101010101010101010101010 e"
0N
b11 L
b11 `
b11 h
b11 o
b0 d
b11 y
b11 /"
b11 7"
b11 >"
b11 H"
b11 \"
b11 d"
b11 k"
08
#13
b10101010101010101010101010101010 :"
18
#14
b0 ^"
b1 B"
b0 1"
08
#15
b10101010101010101010101010101010 ;"
b0 3"
b0 2"
b0 0"
18
b0 3
b0 w
b0 '"
1=
05
#16
b1111 *
b1111 D
1)
1$
0Q
1}
0|
b10 B"
08
#17
b0 &"
b0 )"
b10101010101010101010101010101010 <"
b1111 F
b100 g
b100 6"
b100 c"
18
b1111 0
b1111 u
b1111 $"
b10111011101110111011101110111011 :
b10111011101110111011101110111011 x
b10111011101110111011101110111011 ."
16
0=
#18
b1011 *
b1011 D
0(
1%
ze
z4"
za"
z$
1#
1&
bz !
bz I
bz V
bz j
bz v
bz %"
bz 9"
bz E"
bz R"
bz f"
bz "
bz G
bz T
bz i
bz t
bz #"
bz 8"
bz C"
bz P"
bz e"
1-
b1111 .
b1111 E
b100 H"
b100 \"
b100 d"
b100 k"
b11 B"
b1 3"
b1 2"
b1 0"
1~
1|
0}
b100 y
b100 /"
b100 7"
b100 >"
b100 L
b100 `
b100 h
b100 o
08
#19
z#
z&
b1011 F
bz m"
bz @"
bz q
b0 c"
b0 6"
b0 g
18
#20
z%
0,
0f
1N
b0 L
b0 `
b0 h
b0 o
b0 a
1{
b0 y
b0 /"
b0 7"
b0 >"
1J"
b0 H"
b0 \"
b0 d"
b0 k"
b1011 .
b1011 E
08
#21
0R
18
#22
15"
08
#23
1$
1!"
b1 6"
18
#24
1%
0$
0e
04"
0a"
b0 !
b0 I
b0 V
b0 j
b0 v
b0 %"
b0 9"
b0 E"
b0 R"
b0 f"
b0 "
b0 G
b0 T
b0 i
b0 t
b0 #"
b0 8"
b0 C"
b0 P"
b0 e"
b1 y
b1 /"
b1 7"
b1 >"
08
#25
1#
1&
b0 s
b0 r
b0 q
b0 m"
b11 g
b11 6"
b11 c"
18
#26
0%
0$
1e
14"
1a"
0#
0&
b1111 !
b1111 I
b1111 V
b1111 j
b1111 v
b1111 %"
b1111 9"
b1111 E"
b1111 R"
b1111 f"
b10111011101110111011101110111011 "
b10111011101110111011101110111011 G
b10111011101110111011101110111011 T
b10111011101110111011101110111011 i
b10111011101110111011101110111011 t
b10111011101110111011101110111011 #"
b10111011101110111011101110111011 8"
b10111011101110111011101110111011 C"
b10111011101110111011101110111011 P"
b10111011101110111011101110111011 e"
b11 H"
b11 \"
b11 d"
b11 k"
b0 3"
0{
b11 y
b11 /"
b11 7"
b11 >"
b11 L
b11 `
b11 h
b11 o
08
#27
b10111011101110111011101110111011 k
b0 `"
b0 _"
b0 ]"
18
1>
06
#28
b1111 *
b1111 D
1(
1$
b1 s
0~
1L"
0K"
08
#29
b10111011101110111011101110111011 l
b0 S"
b0 V"
b1111 F
b0 c
b100 g
b100 6"
b100 c"
18
0A
b0 4
b0 F"
b0 T"
b1111 1
b1111 D"
b1111 Q"
b10 2
b10 J
b10 X
1<
#30
1%
ze
z4"
za"
z$
bz !
bz I
bz V
bz j
bz v
bz %"
bz 9"
bz E"
bz R"
bz f"
bz "
bz G
bz T
bz i
bz t
bz #"
bz 8"
bz C"
bz P"
bz e"
1#
1&
1,
b1111 .
b1111 E
b1 `"
b1 _"
b1 ]"
b100 H"
b100 \"
b100 d"
b100 k"
b100 y
b100 /"
b100 7"
b100 >"
b10 s
1P
0O
b100 L
b100 `
b100 h
b100 o
08
#31
z#
z&
bz m"
b1 Z"
bz q
b10 Z
b0 c"
b0 6"
b0 g
18
b1 4
b1 F"
b1 T"
b11001100110011001100110011001100 ;
b11001100110011001100110011001100 G"
b11001100110011001100110011001100 ["
0>
0<
#32
0)
z%
b101 *
b101 D
0'
1O
0P
b0 L
b0 `
b0 h
b0 o
b1 c
b1 a
b1 d
05"
1{
b0 y
b0 /"
b0 7"
b0 >"
b0 0"
1K"
0L"
b0 H"
b0 \"
b0 d"
b0 k"
b10 _"
b10 ]"
b10 `"
08
#33
b1101 F
0!"
18
#34
0-
b1101 .
b1101 E
08
#35
18
#36
1f
08
#37
1$
1R
b1 g
18
