device/target.v
module Target_Controller(
    input clk, inout[31:0] AD, input[3:0] C_BE, output devsel, output trdy, input[2:0] state, input fvalid, input[1:0] tar_address, input frame
    );

parameter[3:0]
/* Command value for read = 1, write = 0 */
read = 1, write = 0;

parameter[2:0] idle=0, address=1, turnaround=2, data=3, finish=4;
reg[31:0] add;
reg[31:0] memory[0:9];
reg[3:0] mp;
wire[31:0] mem1; assign mem1 = memory[0];
wire[31:0] mem2; assign mem2 = memory[1];    
wire[31:0] mem3; assign mem3 = memory[2];
wire[31:0] mem4; assign mem4 = memory[3];
reg[3:0] command;
always @ (posedge clk) begin
    if (!frame && state == idle) begin
        add <= AD;
        command <= C_BE; 
        mp <= 0;
    end
    if(state == data && fvalid && add === tar_address) begin
        if(C_BE[0]) begin
            memory[mp][7:0] <= AD[7:0]; 
        end
        if(C_BE[1]) begin
            memory[mp][15:8] <= AD[15:8];  
        end
        if(C_BE[2]) begin
            memory[mp][23:16] <= AD[23:16];  
        end
        if(C_BE[3]) begin
            memory[mp][31:24] <= AD[31:24];  
        end
    end
    if(state == finish) begin
        add <= 32'hZZZZZZZZ;
    end
end
always @ (negedge clk) begin
    if (state == data && command == write && fvalid && add === tar_address) begin
        mp <= mp + 1; 
    end
end

assign devsel = (state == data && add === tar_address) ? 0 : ((state == finish || state == turnaround || !frame) && add === tar_address) ? 1 : 1'bz;
assign trdy = (state == data && add === tar_address) ? 0 : ((state == finish || state == turnaround || !frame) && add === tar_address) ? 1 : 1'bz;
assign AD = (state == data && add === tar_address && command == read) ?  memory[mp]: 32'hZZZZZZZZ;

endmodule   //target read module

device/initiator.v
module Initiator_Controller(
    input [1:0]devaddress, input[3:0] BE, input force_req, input rd_wr, input[31:0] write_data,
    input clk, inout[31:0] AD, output[3:0] C_BE, output frame, output irdy,
    output req,
    input[2:0] state, input fcount, input fend_count, input ffinished, input fvalid, input bus_is_mine,
    input fburst    // extra input for burst read (active high)
    );

/*
  **When in burst mode the intiator continues in data phases until either maximum failed transfers 
    or fburst signalis deasserted.
  **In Normal mode the intiator completes one data transfer and continues to the next transaction.
*/

reg[3:0] command[0:3];
wire[3:0] comm;
assign comm = command[0];
/*
    when force_req signal is asserted, at every positive edge a corresponding target-address and command is saved
    in internal memory  
*/
always @ (posedge clk) begin
    if (fcount) begin
        memory[9 - counter] <= devaddress;
        command[counter] <= rd_wr;
    end
end

parameter[2:0]    
idle=0, address=3'b001, turnaround=3'b010, data=3'b011, finish=3'b100;  //states are declared in State_Machine module

/*************************** count number of required transactions by master ******************************/
            /* frame shall not get asserted before force_req signal gets deasserted */

reg[2:0] failed_counter;        //count the cycles at which the target hasn't responded ** max limit 5 cycles
reg [1:0] counter, max;         //counts and saves the number of required transactions
always @ (negedge clk) begin
    if(fcount) begin     
        counter <= counter + 1; 
        max <= counter + 1;
        failed_counter <= 0;
    end
    if (state == finish && (!fburst || failed_counter > 4) && bus_is_mine) begin
        counter <= counter - 1; 
        failed_counter <= 0;
    end
    if ((state == data || state == turnaround) && !fvalid && fburst) begin
        failed_counter <= failed_counter + 1;
    end
    if (state == data && fvalid) begin
        failed_counter <= 0;
    end
end
always @ (posedge force_req) begin
    counter <= 0;
    max <= 0;  
    mp <= 0;
end

////////////////////////////////////* send request to arbiter *////////////////////////////////////////////////
assign req = (fend_count === 1 && 
                ((counter && 
                (!bus_is_mine || (bus_is_mine && state == idle) || (bus_is_mine && fburst && failed_counter < 4))
                || counter > 1))) ? 0 : 1; // MUST REVIEW

////////////////////////////////////////////* set frame *////////////////////////////////////////////////////
assign frame = (bus_is_mine === 1 && state != finish && counter) ? ( (state == address || ( (state == data || state == turnaround ) && (fburst && (failed_counter < 4) ) ) ) ? 0 : 1) : 1'bz;  //multi transactions 

///////////////////////////////////////////* set AD with address *//////////////////////////////////////////
assign AD = (state == address && bus_is_mine === 1) ? memory[9 - max + counter] : (bus_is_mine && command[max-counter] === 0 && state === data) ? write_data : 32'hZZZZZZZZ;
assign C_BE = (state == address && bus_is_mine === 1) ? command[max-counter] : ( (state === data && bus_is_mine) ? BE : 4'bzzzz );

////////////////////////////////////////////* set irdy *////////////////////////////////////////////////////
assign irdy = (bus_is_mine === 1 && (state == turnaround || state == data)) ? 0 : ( (bus_is_mine === 1 && (state == finish || state == address) ) ? 1 : 1'bz );

////////////////////////////////////////////* read data *////////////////////////////////////////////////////
                            /* read data is saved in this internal memory */

reg[2:0] mp;            //memory pointer
reg[31:0] memory[9:0];  //multi transaction 
wire[31:0] mem1, mem2, mem3, mem4, mem9, mem10;
assign mem1 = memory[0];
assign mem2 = memory[1];
assign mem3 = memory[2];
assign mem4 = memory[3];
assign mem9 = memory[8];
assign mem10 = memory[9];

always @ (posedge clk) begin
    if (bus_is_mine && (state == data && fvalid) && command[max-counter] == 1) begin
        memory[mp] <= AD;
    end
    if (state == idle && counter == 0) begin
        mp <= 0; 
    end
    if (fcount) begin
        memory[9-mp] <= devaddress; 
    end

end
always @ (negedge clk) begin    // increment memory pointer
    if (bus_is_mine && (state == data && fvalid) && mp < 8 && command[max-counter] == 1) begin
        mp <= mp + 1; 
    end
    if (fcount) begin
        mp <= mp + 1; 
    end
    if (state == address) begin
        mp <= 0; 
    end
end

endmodule   //master read & write module

device/state_machine.v
module State_Machine(
    frame, irdy, trdy, devsel, state, clk, force_req, burst, req, gnt, rd_wr, fcount, fend_count, ffinished, fvalid, fburst, bus_is_mine
);

/*
    This state machine is valid for both read and write transactions
    for read: rd_wr = 1
    for write: rd_wr = 0
*/

input wire frame, irdy, trdy, devsel, clk, force_req, burst, req, gnt, rd_wr;
output reg[2:0] state;
reg[2:0] next_state;

parameter[2:0] 
/*
There are five states:
1. idle: here the bus is free (with respect to the device)
2. address: the initiator has asserted the frame and put a valid address on AD lines
3. turnaround: in case of read transaction the target must wait for two cylces after the frame being asserted
    to put valid data on AD and hence assert trdy
4. data: here data tranfers may occur depending on irdy & trdy (fvalid flag)
5. finish: all required transfers have occured and turnaround cycle ouccurs 
*/
idle=0, address=1, turnaround=2, data=3, finish=4;

output reg          //flags that contributes in synchronization of bus lines
    fcount,         //indicates assertion of force_req signal
    fend_count,     //indicates deassertion of force_req signal
    ffinished,      //indicates finished transaction and free bus
    fvalid,         //indicates that a valid data transfer may occur next positive edge of clock **combinational
    fburst,
    bus_is_mine;
reg fgnt;           //indicates a granted bus ownership

always @(negedge clk) begin
    state <= next_state;      
    if (force_req) begin
        fend_count <= 0;
        fcount <= 1; 
    end
    if (!force_req && fcount) begin
        fcount <= 0;
        fend_count <= 1;
    end
    if (state == address) begin
        ffinished <= 0; 
    end
    if (state == finish) begin
        ffinished <= 1;
    end
    if (!gnt) begin
        fgnt <= 1; 
    end else begin
        fgnt <= 0; 
    end
    if (burst) begin
        fburst <= 1; 
    end else begin
        fburst <= 0; 
    end
end

always @(posedge clk) begin
    case (state)

        idle: begin
            fvalid = 1;
            bus_is_mine = 0 ;
            if (fgnt && !req) begin
                next_state = address;
                bus_is_mine = 1;
            end
            if (!frame && !bus_is_mine) begin
                if (rd_wr) begin
                    next_state = turnaround;               
                end
                else begin
                    next_state = data;
                end
            end
        end

        address: begin
            if (!frame) begin
                if (rd_wr) begin
                    next_state = turnaround;               
                end
                else begin
                    next_state = data;
                end
            end
            fvalid = 1;
        end

        turnaround: begin
            fvalid = 1;
            next_state = data;
        end

        data: begin
            if(fgnt === 0 && bus_is_mine) begin
                next_state = finish; 
            end
            if (frame) begin
                next_state = finish; 
            end
            if(trdy === 0 && irdy === 0 && devsel === 0) begin
                fvalid = 1; 
            end else begin
                fvalid = 0; 
            end
        end

        finish: begin 
            next_state = idle; 
        end

        default: next_state = idle; //for initializing
    endcase
end

endmodule // State_Machine

device/device.v
module Controller(
    input [1:0]devaddress, input [3:0] BE, input force_req, input rd_wr, input[31:0]  write_data, input burst,
    input clk, inout[31:0] AD, inout[3:0] C_BE, inout devsel, inout frame, inout irdy, inout trdy,
    input gnt, output req,
    input reset_address //active high
);

wire[2:0] state;
reg[1:0] tar_add;
always @ (reset_address) begin
    if (reset_address) begin
        tar_add <= devaddress;
    end
end

State_Machine sm(
    frame, irdy, trdy, devsel, state, clk, force_req, burst, req, gnt, C_BE[0], fcount, fend_count, ffinished, fvalid, fburst, bus_is_mine
);

Initiator_Controller ic(
    devaddress, BE, force_req, rd_wr, write_data, clk, AD, C_BE, frame, irdy, req, 
    state, fcount, fend_count, ffinished, fvalid, bus_is_mine, fburst
);

Target_Controller tc(
    clk, AD, C_BE, devsel, trdy, state, fvalid, tar_add, frame
);


endmodule

device/testbench1.v
`timescale 1us/1us
module test;

    parameter A = 2'b01, B= 2'b00;
    reg[1:0] addressA; reg[1:0] addressB;
    reg[31:0] datA; reg[31:0] datB;
    reg[3:0] BE_A; reg[3:0] BE_B;
    wire[3:0] C_BE;
    reg force_reqA, force_reqB, clk, gntA, gntB, rd_wrA, rd_wrB, burstA, burstB, rframe, reset_add;
    inout frame, irdy, reqA, reqB;
    // assign frame = rframe;
    wire[31:0] d;
    initial begin
        $dumpfile("test.vcd");
        $dumpvars(0,test);
        rframe = 1'bz;
        gntA = 1; gntB = 1; force_reqA = 0; force_reqB = 0; rd_wrA = 0; rd_wrB = 0;
        burstA = 0; burstB = 0; reset_add = 1; addressA = A; addressB = B;
        clk = 0;
        #1
        reset_add = 0;
        force_reqA = 1;
        addressA = B;
        rd_wrA = 0;
        #2
        force_reqA = 0;
        gntA = 0;
        burstA = 1;
        datA = 32'hAAAAAAAA;
        BE_A = 4'b1011;
        #8
        burstA = 0;
        
        force_reqB = 1;
        addressB = A;
        gntB = 0;
        rd_wrB = 0;
        #2
        force_reqB = 0;
        burstB = 1;
        datB = 32'hBBBBBBBB;
        BE_B = 4'b1111;
        #8
        burstB = 0;
        
        
        # 40 $finish;
    end

    always #1 clk = ~clk;

    Controller deviceA( addressA,  BE_A,  force_reqA,  rd_wrA, datA, burstA,
     clk,  d,  C_BE,  devsel,  frame,  irdy,  trdy,
     gntA,  reqA,
     reset_add
     );
     Controller deviceB( addressB,  BE_B,  force_reqB,  rd_wrB, datB, burstB,
     clk,  d,  C_BE,  devsel,  frame,  irdy,  trdy,
     gntB,  reqB,
     reset_add
     );

endmodule //

device/test.vcd
$date
	Thu Dec 27 00:51:16 2018
$end
$version
	Icarus Verilog
$end
$timescale
	1us
$end
$scope module test $end
$var wire 4 ! C_BE [3:0] $end
$var wire 32 " d [31:0] $end
$var wire 1 # devsel $end
$var wire 1 $ frame $end
$var wire 1 % irdy $end
$var wire 1 & trdy $end
$var wire 1 ' reqB $end
$var wire 1 ( reqA $end
$var reg 4 ) BE_A [3:0] $end
$var reg 4 * BE_B [3:0] $end
$var reg 2 + addressA [1:0] $end
$var reg 2 , addressB [1:0] $end
$var reg 1 - burstA $end
$var reg 1 . burstB $end
$var reg 1 / clk $end
$var reg 32 0 datA [31:0] $end
$var reg 32 1 datB [31:0] $end
$var reg 1 2 force_reqA $end
$var reg 1 3 force_reqB $end
$var reg 1 4 gntA $end
$var reg 1 5 gntB $end
$var reg 1 6 rd_wrA $end
$var reg 1 7 rd_wrB $end
$var reg 1 8 reset_add $end
$var reg 1 9 rframe $end
$scope module deviceA $end
$var wire 32 : AD [31:0] $end
$var wire 4 ; BE [3:0] $end
$var wire 4 < C_BE [3:0] $end
$var wire 1 - burst $end
$var wire 1 / clk $end
$var wire 2 = devaddress [1:0] $end
$var wire 1 # devsel $end
$var wire 1 2 force_req $end
$var wire 1 $ frame $end
$var wire 1 4 gnt $end
$var wire 1 % irdy $end
$var wire 1 6 rd_wr $end
$var wire 1 8 reset_address $end
$var wire 1 & trdy $end
$var wire 32 > write_data [31:0] $end
$var wire 3 ? state [2:0] $end
$var wire 1 ( req $end
$var wire 1 @ fvalid $end
$var wire 1 A ffinished $end
$var wire 1 B fend_count $end
$var wire 1 C fcount $end
$var wire 1 D fburst $end
$var wire 1 E bus_is_mine $end
$var reg 2 F tar_add [1:0] $end
$scope module ic $end
$var wire 32 G AD [31:0] $end
$var wire 4 H BE [3:0] $end
$var wire 4 I C_BE [3:0] $end
$var wire 1 / clk $end
$var wire 4 J comm [3:0] $end
$var wire 2 K devaddress [1:0] $end
$var wire 1 2 force_req $end
$var wire 1 $ frame $end
$var wire 1 % irdy $end
$var wire 32 L mem1 [31:0] $end
$var wire 32 M mem10 [31:0] $end
$var wire 32 N mem2 [31:0] $end
$var wire 32 O mem3 [31:0] $end
$var wire 32 P mem4 [31:0] $end
$var wire 32 Q mem9 [31:0] $end
$var wire 1 6 rd_wr $end
$var wire 32 R write_data [31:0] $end
$var wire 3 S state [2:0] $end
$var wire 1 ( req $end
$var wire 1 @ fvalid $end
$var wire 1 A ffinished $end
$var wire 1 B fend_count $end
$var wire 1 C fcount $end
$var wire 1 D fburst $end
$var wire 1 E bus_is_mine $end
$var reg 2 T counter [1:0] $end
$var reg 3 U failed_counter [2:0] $end
$var reg 2 V max [1:0] $end
$var reg 3 W mp [2:0] $end
$upscope $end
$scope module sm $end
$var wire 1 - burst $end
$var wire 1 / clk $end
$var wire 1 # devsel $end
$var wire 1 2 force_req $end
$var wire 1 $ frame $end
$var wire 1 4 gnt $end
$var wire 1 % irdy $end
$var wire 1 X rd_wr $end
$var wire 1 ( req $end
$var wire 1 & trdy $end
$var reg 1 E bus_is_mine $end
$var reg 1 D fburst $end
$var reg 1 C fcount $end
$var reg 1 B fend_count $end
$var reg 1 A ffinished $end
$var reg 1 Y fgnt $end
$var reg 1 @ fvalid $end
$var reg 3 Z next_state [2:0] $end
$var reg 3 [ state [2:0] $end
$upscope $end
$scope module tc $end
$var wire 32 \ AD [31:0] $end
$var wire 4 ] C_BE [3:0] $end
$var wire 1 / clk $end
$var wire 1 # devsel $end
$var wire 1 $ frame $end
$var wire 1 @ fvalid $end
$var wire 32 ^ mem1 [31:0] $end
$var wire 32 _ mem2 [31:0] $end
$var wire 32 ` mem3 [31:0] $end
$var wire 32 a mem4 [31:0] $end
$var wire 3 b state [2:0] $end
$var wire 2 c tar_address [1:0] $end
$var wire 1 & trdy $end
$var reg 32 d add [31:0] $end
$var reg 4 e command [3:0] $end
$var reg 4 f mp [3:0] $end
$upscope $end
$upscope $end
$scope module deviceB $end
$var wire 32 g AD [31:0] $end
$var wire 4 h BE [3:0] $end
$var wire 4 i C_BE [3:0] $end
$var wire 1 . burst $end
$var wire 1 / clk $end
$var wire 2 j devaddress [1:0] $end
$var wire 1 # devsel $end
$var wire 1 3 force_req $end
$var wire 1 $ frame $end
$var wire 1 5 gnt $end
$var wire 1 % irdy $end
$var wire 1 7 rd_wr $end
$var wire 1 8 reset_address $end
$var wire 1 & trdy $end
$var wire 32 k write_data [31:0] $end
$var wire 3 l state [2:0] $end
$var wire 1 ' req $end
$var wire 1 m fvalid $end
$var wire 1 n ffinished $end
$var wire 1 o fend_count $end
$var wire 1 p fcount $end
$var wire 1 q fburst $end
$var wire 1 r bus_is_mine $end
$var reg 2 s tar_add [1:0] $end
$scope module ic $end
$var wire 32 t AD [31:0] $end
$var wire 4 u BE [3:0] $end
$var wire 4 v C_BE [3:0] $end
$var wire 1 / clk $end
$var wire 4 w comm [3:0] $end
$var wire 2 x devaddress [1:0] $end
$var wire 1 3 force_req $end
$var wire 1 $ frame $end
$var wire 1 % irdy $end
$var wire 32 y mem1 [31:0] $end
$var wire 32 z mem10 [31:0] $end
$var wire 32 { mem2 [31:0] $end
$var wire 32 | mem3 [31:0] $end
$var wire 32 } mem4 [31:0] $end
$var wire 32 ~ mem9 [31:0] $end
$var wire 1 7 rd_wr $end
$var wire 32 !" write_data [31:0] $end
$var wire 3 "" state [2:0] $end
$var wire 1 ' req $end
$var wire 1 m fvalid $end
$var wire 1 n ffinished $end
$var wire 1 o fend_count $end
$var wire 1 p fcount $end
$var wire 1 q fburst $end
$var wire 1 r bus_is_mine $end
$var reg 2 #" counter [1:0] $end
$var reg 3 $" failed_counter [2:0] $end
$var reg 2 %" max [1:0] $end
$var reg 3 &" mp [2:0] $end
$upscope $end
$scope module sm $end
$var wire 1 . burst $end
$var wire 1 / clk $end
$var wire 1 # devsel $end
$var wire 1 3 force_req $end
$var wire 1 $ frame $end
$var wire 1 5 gnt $end
$var wire 1 % irdy $end
$var wire 1 '" rd_wr $end
$var wire 1 ' req $end
$var wire 1 & trdy $end
$var reg 1 r bus_is_mine $end
$var reg 1 q fburst $end
$var reg 1 p fcount $end
$var reg 1 o fend_count $end
$var reg 1 n ffinished $end
$var reg 1 (" fgnt $end
$var reg 1 m fvalid $end
$var reg 3 )" next_state [2:0] $end
$var reg 3 *" state [2:0] $end
$upscope $end
$scope module tc $end
$var wire 32 +" AD [31:0] $end
$var wire 4 ," C_BE [3:0] $end
$var wire 1 / clk $end
$var wire 1 # devsel $end
$var wire 1 $ frame $end
$var wire 1 m fvalid $end
$var wire 32 -" mem1 [31:0] $end
$var wire 32 ." mem2 [31:0] $end
$var wire 32 /" mem3 [31:0] $end
$var wire 32 0" mem4 [31:0] $end
$var wire 3 1" state [2:0] $end
$var wire 2 2" tar_address [1:0] $end
$var wire 1 & trdy $end
$var reg 32 3" add [31:0] $end
$var reg 4 4" command [3:0] $end
$var reg 4 5" mp [3:0] $end
$upscope $end
$upscope $end
$upscope $end
$enddefinitions $end
#0
$dumpvars
bx 5"
bx 4"
bx 3"
b0 2"
bx 1"
bx 0"
bx /"
bx ."
bx -"
bz ,"
bz +"
bx *"
bx )"
0("
z'"
bx &"
bx %"
bx $"
bx #"
bx ""
bx !"
bx ~
bx }
bx |
bx {
bx z
bx y
b0 x
bx w
bz v
bx u
bz t
b0 s
xr
0q
xp
xo
xn
xm
bx l
bx k
b0 j
bz i
bx h
bz g
bx f
bx e
bx d
b1 c
bx b
bx a
bx `
bx _
bx ^
bz ]
bz \
bx [
bx Z
0Y
zX
bx W
bx V
bx U
bx T
bx S
bx R
bx Q
bx P
bx O
bx N
bx M
bx L
b1 K
bx J
bz I
bx H
bz G
b1 F
xE
0D
xC
xB
xA
x@
bx ?
bx >
b1 =
bz <
bx ;
bz :
z9
18
07
06
15
14
03
02
bx 1
bx 0
0/
0.
0-
b0 ,
b1 +
bx *
bx )
1(
1'
z&
z%
z$
z#
bz "
bz !
$end
#1
b0 W
b0 V
b0 T
b0 Z
b0 )"
1/
b0 +
b0 =
b0 K
12
08
#2
b0 l
b0 ""
b0 *"
b0 1"
1C
0B
b0 ?
b0 S
b0 [
b0 b
0/
#3
b0 J
b0 M
0r
1m
0E
1@
1/
b1011 )
b1011 ;
b1011 H
b10101010101010101010101010101010 0
b10101010101010101010101010101010 >
b10101010101010101010101010101010 R
1-
04
02
#4
0(
1D
1Y
1B
0C
b0 U
b1 V
b1 T
b1 W
0/
#5
1$
1E
b1 Z
1/
#6
1%
0$
0X
0'"
b0 !
b0 <
b0 I
b0 ]
b0 i
b0 v
b0 ,"
b0 "
b0 :
b0 G
b0 \
b0 g
b0 t
b0 +"
b1 ?
b1 S
b1 [
b1 b
0/
#7
1#
1&
b0 5"
b0 4"
b0 3"
b11 )"
b11 Z
1/
#8
0%
0$
1X
1'"
0#
0&
b1011 !
b1011 <
b1011 I
b1011 ]
b1011 i
b1011 v
b1011 ,"
b10101010101010101010101010101010 "
b10101010101010101010101010101010 :
b10101010101010101010101010101010 G
b10101010101010101010101010101010 \
b10101010101010101010101010101010 g
b10101010101010101010101010101010 t
b10101010101010101010101010101010 +"
0A
b11 ?
b11 S
b11 [
b11 b
b0 W
b11 l
b11 ""
b11 *"
b11 1"
0/
#9
b10101010xxxxxxxx1010101010101010 -"
1/
#10
b1 5"
b0 $"
0/
#11
b10101010xxxxxxxx1010101010101010 ."
b0 &"
b0 %"
b0 #"
1/
05
b1 ,
b1 j
b1 x
13
0-
#12
1(
1$
0D
1("
1p
0o
b10 5"
0/
#13
b0 w
b1 z
b10101010xxxxxxxx1010101010101010 /"
b100 Z
b100 )"
1/
b1111 *
b1111 h
b1111 u
b10111011101110111011101110111011 1
b10111011101110111011101110111011 k
b10111011101110111011101110111011 !"
1.
03
#14
0'
1%
zX
z'"
z$
1#
1&
bz !
bz <
bz I
bz ]
bz i
bz v
bz ,"
bz "
bz :
bz G
bz \
bz g
bz t
bz +"
b11 5"
b1 &"
b1 %"
b1 #"
1q
1o
0p
b100 l
b100 ""
b100 *"
b100 1"
b100 ?
b100 S
b100 [
b100 b
0/
#15
z#
z&
bz 3"
bz d
b0 )"
b0 Z
1/
#16
z%
1A
b0 ?
b0 S
b0 [
b0 b
b0 T
1n
b0 l
b0 ""
b0 *"
b0 1"
0/
#17
1$
0E
1r
b1 )"
1/
#18
1%
0$
0X
0'"
b0 !
b0 <
b0 I
b0 ]
b0 i
b0 v
b0 ,"
b1 "
b1 :
b1 G
b1 \
b1 g
b1 t
b1 +"
b1 l
b1 ""
b1 *"
b1 1"
0/
#19
1#
1&
b0 f
b0 e
b1 d
b11 )"
b11 Z
1/
#20
0%
0$
0#
0&
1X
1'"
b1111 !
b1111 <
b1111 I
b1111 ]
b1111 i
b1111 v
b1111 ,"
b10111011101110111011101110111011 "
b10111011101110111011101110111011 :
b10111011101110111011101110111011 G
b10111011101110111011101110111011 \
b10111011101110111011101110111011 g
b10111011101110111011101110111011 t
b10111011101110111011101110111011 +"
b11 ?
b11 S
b11 [
b11 b
0n
b11 l
b11 ""
b11 *"
b11 1"
b0 &"
0/
#21
b10111011101110111011101110111011 ^
1/
0.
#22
1'
1$
0q
b1 f
0/
#23
b10111011101110111011101110111011 _
b100 )"
b100 Z
1/
#24
1%
zX
z'"
z$
1#
1&
bz !
bz <
bz I
bz ]
bz i
bz v
bz ,"
bz "
bz :
bz G
bz \
bz g
bz t
bz +"
b100 ?
b100 S
b100 [
b100 b
b10 f
b100 l
b100 ""
b100 *"
b100 1"
0/
#25
z#
z&
bz d
b0 Z
b0 )"
1/
#26
z%
b0 #"
1n
b0 l
b0 ""
b0 *"
b0 1"
b0 ?
b0 S
b0 [
b0 b
0/
#27
0r
1/
