controller/state_machine.v
module State_Machine(
    frame, irdy, trdy, devsel, state, clk
);

input wire frame, irdy, trdy, devsel, clk;
output reg[2:0] state;
reg[2:0] next_state;

parameter[2:0] 
/* phases are four; 
1. idle : bus is free.
2. address : address only valid for one cycle.
3. data wait : bus is on hold as any of #RDY signals are deasserted (no transaction occurs).
4. data : transaction occurs.
5. final : final transaction occurs then bus waits for initiator to deassert IRDY.
*/
idle=0, address=1, data_wait=2, data=3, final=4;

always @(negedge clk) begin
    state <= next_state;
end

always @(*) begin
    case (state)

        idle: if (~frame) begin
            next_state = address;
        end

        address: begin
            next_state = data_wait;
        end

        data_wait: if (~irdy & ~trdy & ~devsel) begin
            next_state = data;
        end

        data: if (frame & ~irdy & ~trdy) begin
            next_state = final;
        end
        else if (irdy || trdy) begin
            next_state = data_wait; 
        end

        final: if (irdy) begin
            next_state = idle;
        end

        default: next_state = idle; //for initializing
    endcase
end

endmodule // State_Machine

controller/initiator.v
module Initiator_Controller(
    input [1:0]devaddress, input [3:0] BE, /*output [31:0]data,*/ input force_req, input rd_wr, //force_req active high
    input clk, inout[31:0] AD, output[3:0] C_BE, input devsel, output reg frame, output irdy, input trdy,
    input gnt, output req);


reg[31:0] memory[0:7];

wire wframe, irdy;
always @ (negedge clk) begin
    frame <= wframe;
    // irdy <= irdy;
    if (force_req) begin
        memory[7] <= devaddress;
    end
end

wire [2:0] state;
State_Machine sm (wframe, irdy, trdy, devsel, state, clk);
parameter[2:0]
/* phases are four; 
1. idle : bus is free.
2. address : initiator waiting for a device to identify itself as the target.
3. data wait : bus is on hold as any of #RDY signals are deasserted (no transaction occurs).
4. data : transaction occurs.
5. final : final transaction occurs then bus waits for initiator to deassert IRDY.
*/
idle=0, address=1, data_wait=2, data=3, final=4;

/*************************** count number of required transactions by master ******************************/
/* wframe must not get asserted before force_req signal gets deasserted */
reg [1:0] counter;
always @ (posedge clk) begin
    if(force_req && state == idle) begin     
        counter <= counter + 1; 
    end
    if (state == data || state == final) begin
        counter <= counter - 1; 
    end
end
always @ (posedge force_req) begin
    counter <= 0;
end

////////////////////////////////////* send request to arbiter *////////////////////////////////////////////////
reg bus_is_mine;    // indicate whether the bus is in this controller's command (active high)
assign req = (((~force_req) && counter) && (~bus_is_mine)) ? 0 : 1; // MUST REVIEW
always @ (negedge clk) begin
    if (force_req) begin
        bus_is_mine <= 0; 
    end
    if (~gnt && state == idle && ~bus_is_mine) begin
        bus_is_mine <= 1; 
    end
    if (bus_is_mine && state == final) begin
        bus_is_mine <= 0; 
    end
end

////////////////////////////////////////////* set wframe *////////////////////////////////////////////////////
assign wframe = (bus_is_mine) ? ( (state == idle || counter > 1) ? 0 : 1) : 1'bz;

///////////////////////////////////////////* set AD with address *//////////////////////////////////////////
assign AD = (state == address) ? memory[7] : 32'hZZZZZZZZ;

////////////////////////////////////////////* set irdy *////////////////////////////////////////////////////
assign irdy = (state == data_wait || state == data ||()) ? 0 : ( (state == final) ? 1 : 1'bz );

////////////////////////////////////////////* read data *////////////////////////////////////////////////////
 //for storing entry
reg[2:0] mp;            //memory pointer

always @ (posedge clk) begin
    if (state == data || state == final) begin
        memory[mp] <= AD;
        //mp++;   // illegal // unsynthesizable // accessing memory location mp while changing mp value
    end
    if (state == idle) begin
        mp <= 0; 
    end
end
always @ (negedge clk) begin    // increment memory pointer
    if (state == data || state == final) begin
        mp <= mp + 1; 
    end
end

endmodule

controller2/initiator_tb.v
module test;
    reg[1:0] address;
    wire[31:0] dat;
    reg[3:0] BE;
    wire[3:0] C_BE;
    reg force_req, clk, devsel, trdy, gnt, rd_wr;
    wire frame, irdy, req;
    reg[31:0] AD;
    wire[31:0] d;
    assign d = AD;
    initial begin
        AD = 32'hZZZZZZZZ;
        $dumpfile("test.vcd");
        $dumpvars(0,test);
        trdy = 1; devsel = 1; gnt = 1; force_req = 0;
        clk = 0;
        #4
        force_req = 1;
        address = 2'b01;
        #6
        force_req = 0;
        address = 2'bzz;
        #2
        gnt = 0;
        #2
        gnt = 1;
        #4
        trdy = 0;
        devsel = 0;
        AD = 32'hAAAAAAAA;
        #2
        AD = 32'hBBBBBBBB;

        # 10 $finish;
    end

    always #1 clk = ~clk;

    Initiator_Controller device( address,  BE,  force_req,  rd_wr, //force_req active high
     clk,  d,  C_BE,  devsel,  frame,  irdy,  trdy,
     gnt,  req);

endmodule //

controller/test.vcd
$date
	Sat Dec 22 16:11:01 2018
$end
$version
	Icarus Verilog
$end
$timescale
	1s
$end
$scope module test $end
$var wire 4 ! C_BE [3:0] $end
$var wire 32 " d [31:0] $end
$var wire 1 # req $end
$var wire 1 $ irdy $end
$var wire 1 % frame $end
$var reg 32 & AD [31:0] $end
$var reg 4 ' BE [3:0] $end
$var reg 2 ( address [1:0] $end
$var reg 1 ) clk $end
$var reg 1 * devsel $end
$var reg 1 + force_req $end
$var reg 1 , gnt $end
$var reg 1 - rd_wr $end
$var reg 1 . trdy $end
$scope module device $end
$var wire 32 / AD [31:0] $end
$var wire 4 0 BE [3:0] $end
$var wire 4 1 C_BE [3:0] $end
$var wire 1 ) clk $end
$var wire 2 2 devaddress [1:0] $end
$var wire 1 * devsel $end
$var wire 1 + force_req $end
$var wire 1 , gnt $end
$var wire 1 - rd_wr $end
$var wire 1 . trdy $end
$var wire 1 3 wframe $end
$var wire 3 4 state [2:0] $end
$var wire 1 # req $end
$var wire 1 $ irdy $end
$var reg 1 5 bus_is_mine $end
$var reg 2 6 counter [1:0] $end
$var reg 1 % frame $end
$var reg 3 7 mp [2:0] $end
$scope module sm $end
$var wire 1 ) clk $end
$var wire 1 * devsel $end
$var wire 1 3 frame $end
$var wire 1 $ irdy $end
$var wire 1 . trdy $end
$var reg 3 8 next_state [2:0] $end
$var reg 3 9 state [2:0] $end
$upscope $end
$upscope $end
$upscope $end
$enddefinitions $end
#0
$dumpvars
b0 9
b0 8
bx 7
bx 6
x5
b0 4
x3
bx 2
bz 1
bx 0
bz /
1.
x-
1,
0+
1*
0)
bx (
bx '
bz &
z%
z$
x#
bz "
bz !
$end
#1
b0 7
1)
#2
x%
0)
#3
1)
#4
z3
05
b0 6
1#
0)
b1 (
b1 2
1+
#5
b1 6
1)
#6
z%
0)
#7
b10 6
1)
#8
0)
#9
b11 6
1)
#10
0#
0)
bz (
bz 2
0+
#11
1)
#12
1#
b1 8
03
15
0)
0,
#13
1)
#14
b10 8
b1 "
b1 /
0%
b1 4
b1 9
0)
1,
#15
1)
#16
0$
bz "
bz /
b10 4
b10 9
0)
#17
1)
#18
b11 4
b11 9
b11 8
0)
b10101010101010101010101010101010 "
b10101010101010101010101010101010 /
b10101010101010101010101010101010 &
0*
0.
#19
b10 6
1)
#20
b1 7
0)
b10111011101110111011101110111011 "
b10111011101110111011101110111011 /
b10111011101110111011101110111011 &
#21
b100 8
13
b1 6
1)
#22
b0 8
1$
b10 7
1%
b100 4
b100 9
0)
#23
b0 6
1)
#24
z$
z3
b0 4
b0 9
05
b11 7
0)
#25
b0 7
1)
#26
z%
0)
